{
  "id": "cloudforged",
  "category": "weapons",
  "icon": "assets/icons/weapons/bow/cloudforged.png",
  "title": {
    "ru": "Выкованный из облаков",
    "en": "Cloudforged",
    "zh": "筑云"
  },
  "region": "",
  "rarity": 4,
  "game_version": "4.7",
  "tags": [
    "оружие",
    "лук"
  ],
  "languages": [
    "ru",
    "en",
    "zh"
  ],
  "text": {
    "ru": "Экспериментальный вариант стандартного оружия, выкованный в кузнице Черногорья по поручению Нефритового Равновесия после того, как были изучены охранявшие обитель Тяньхэн древние механизмы.\n\n### История\nДревние говорили, что горы Тяньхэн богаты драгоценными камнями, а в глубинах Разлома кроются залежи нефрита. Земля тысячи камней издревле славилась своим богатством,\nа важнейшим местом добычи и переработки руды всегда считалась кузница Черногорья, которая находится в горах Тяньхэн.\n\nКузница Черногорья построена глубоко в горах. Она состоит из множества мастерских и плавильных печей, соединённых между собой почерневшими от копоти проходами.\nВ смутные времена, когда дикий огонь войны окрашивал землю алым, эти места служили убежищем для живущих поблизости горных племён.\nГоворят, здесь есть забытые ходы, которые ведут в древнее царство глубоко под землёй...\n\nВ «Сборнике каменных табличек» говорится, что тёмные ходы в горах когда-то проделал предок знаменитого в нынешнем Ли Юэ семейства Юнь.\nС той поры род Юнь вошёл в анналы истории как род кузнецов, а его основоположник на протяжении многих поколений остаётся покровителем мастеров и ремесленников.\n\nВ исторических источниках почти не осталось записей об этом человеке...\n«Предок Юнь был настолько искусен, что деревянные соколы и бамбуковые вороны, к которым он приложил руку, летали вокруг него три дня, не садясь на землю. Он достиг наивысшего мастерства».\n\nПервоначально изучение механики и постижение искусства ковки было неразрывно связано с Адептами.\nПоэтому основателя рода Юнь нередко считали учеником Адептов, а его способности приписывали дарам Адептов.\nВ самой известной истории о нём говорится, что во время смуты он сопровождал императора на войну.\nЗа свои воинские заслуги он получил признание трёх Адептов и был посвящён в тайны механики.\n\nГоворят, его способности были настолько чудесны, что он умел срывать облака с неба и возводить из них бесчисленные башни.\nИ даже из самого трухлявого и гнилого дерева он умел вырезать летающих птиц, которых было невозможно отличить от живых.\n«Черногорье выковано из облаков» - эту поговорку слышал каждый житель Ли Юэ.\nПоэты и сказители давно восхищаются контрастом этих двух образов.\nИ хотя легенда о башнях, выкованных из облаков, явно восходит к языковой игре (ведь фамилия «Юнь» имеет значение «облако»),\nтот факт, что основатель рода Юнь посвятил остаток своей жизни кузнице Черногорья и передаче секретов мастерства, остаётся неоспоримым.\n\nЛегенда гласит, что в конце жизни он вознёсся на небо и стал созвездием, оберегающим мастеров и ремесленников.\nНо в конечном счёте легенды это всего лишь легенды. Кузница Черногорья не соткана из облаков и ветра, да и секреты Адептов здесь ни при чём.\nОна была создана бесчисленными ударами зубил и молотков, выточена каплями пота самых обычных мастеров, которые тысячелетиями работали над её созданием.\nВ конце концов, в договоре с Золотым богом ничего не говорилось о том, что решимость смертных не способна превзойти чудеса бессмертных.\n\n«Предок Юнь был настолько искусен, что деревянные соколы и бамбуковые вороны, к которым он приложил руку, летали вокруг него три дня, не садясь на землю. Он достиг наивысшего мастерства».\nСкалы он превращал в мастерские, а облака - в высокие башни. В горах Тяньхэн он создал кузницу Черногорья. И посему говорят, что его труды принесли людям великую пользу.\nИ сказал Юнь: \"Какая работа зовётся мастерской? А какая неумелой? Работа, что идёт на пользу людям, зовётся мастерской. Всё прочее - работа неумелая\"».",
    "en": "A prototype for a standard-issue weapon the Yuheng commissioned from Blackcliff Forge after having analyzed the ancient mechanisms that protected the adeptal abode upon Tianheng.\n\n### Story\nThe ancients say that the mountains of Mt. Tianheng are filled with gems, and the depths of The Chasm are rich with jade. The nation of a thousand hills has long been known for its abundance,\nAnd its most critical mining and smelting facilities are located in Blackcliff Forge, carved into Mt. Tianheng itself.\n\nThe Forge was constructed by excavating the mountains, with countless workshops, furnaces, and connecting tunnels blasted black by dust.\nIn the tumultuous years when the fires of war dyed the land red, this place was also where the ancestors of the mountain tribes sought shelter.\nIt is even said that long-forgotten passages are within, tunnels to an ancient underground realm that lies in the deep places beneath the earth...\n\nAccording to the Stone Tablet Compilations, the first to carve the darkened paths through the mountains was the founder of the famous Yun family of Liyue.\nFrom that time hence, their clan, a house of smiths, has taken its place on the stage of history, regarded as honored progenitors by countless generations of artisans thereafter.\n\nAs for the stories of that person, the annals of history leave but a scant few lines—\n\"Such was Yun's ingenious craft that wood and bamboo might be carved into birds who would fly for three days without landing. Such were the works considered the apex of artisanry.\"\n\nThe study of mechanisms and the art of forging were all initially inextricably intertwined with the adepti.\nAs such, the founder was oft regarded as an apprentice of the adepti, and the techniques employed by said founder considered adepti teachings.\nThe tale most widely known today is that this personage once fought alongside Rex Lapis on campaign,\nAnd having accomplished much, was acknowledged by three adepti, one after the other, and was granted instruction in secret mechanical arts.\n\nLegend has it that these divine techniques were such that even clouds could be plucked from the skies with which manses might be molded,\nAnd even the rotting, wasting wood could be fashioned into moving birds and beasts, so alike to life as to confound the observing eye.\nAs such, the phrase \"The Blackcliff, forged from clouds\" has long been widely known in Liyue,\nAnd poets and storytellers have long delighted in the contrast between the two images.\nThough the legend of \"cloud-forging\" is a fanciful latter-day play on the family name \"Yun\" meaning \"cloud,\"\nNone dispute that the rest of the founder's life was dedicated to the Blackcliff Forge and the teaching of craftsmanship.\n\nAt life and legend's end, the founder ascended in heavenly light, becoming the guardian star of artisanry.\nStill, legends are naught but legends. It was no adeptal art that built the Forge, nor was it woven of whisps of wind and cloud.\nInstead, it was chiseled out one flake and one hammerstroke at a time, by the pouring sweat of countless ordinary artisans' brows over long centuries.\nDeus Auri's contract never stipulated that mortal resolve could never surpass adeptal miracles, after all.\n\n\"Such was Yun's ingenious craft that wood and bamboo might be carved into birds who would fly for three days without landing. Such were the works considered the apex of artisanry.\"\n\"Yet Yun's life and career were spent working rock into workshops, and molding clouds into manses. Thus was the Blackcliff forged in Tianheng, that the well-being of all the people might be served.\"\n\"For thus Yun said: What is clever? And what is clumsy? That which benefits the people is clever, and that which does otherwise is clumsy.\"",
    "zh": "解析昔日拱卫天衡的仙家机关后，由玉衡星委托黑岩厂锻造的实验型制式兵器。\n\n### 故事\n古语有云，天衡叠嶂连璧生，岩层渊薮玉辉蕴。千岩之国向来以富饶闻名于世，\n而其中最重要的矿藏产地与冶炼锻造之所，便是坐落于天衡山中的「黑岩厂」。\n\n「黑岩厂」乃是掘空山岳所建，无数工坊、熔炉与被尘灰灼得黢黑的甬道勾连，\n在纷乱的烽燧染红大地的年岁，此地亦被嶙峋岩山诸部族的先民用作避难之所。\n据说，其中有一些早已为世人所遗忘的古老甬道，甚至能通往大地深处的古国…\n\n据《石书辑录》所载，最初修凿山中黯道之人，正是如今璃月名门云家的开祖。\n作为锻造世家的云氏自此登上历史的戏台，其人亦被后世无数工匠尊奉为先师。\n\n至于其人的记载，青史中不过寥寥数行——\n「有云氏之巧，斫木为鸢，削竹为鹊，游飏三日而不集，是谓天下至工」\n\n无论是机关之学还是锻造之术，最初都与仙家密不可分，\n正因如此，其人常被视作仙家学徒，其技亦被称作仙授。\n根据今人广知的说法，其曾于天纪俶扰之时随帝君征战，\n树功立业，先后蒙受三位仙君赏识，获赐机关秘术之教。\n\n传说其技法之神妙足以将高天之云摘下，筑成无数楼阁，\n亦能将最为劣质的朽木錾作奔走的鸟兽，令人难辨真伪。\n所谓「黑岩筑于云」的说法，如今在璃月早已广为人知，\n二者在意象上的冲突，也向来为诗家与说书人津津乐道。\n尽管「筑云」的传说不过是后世基于其姓氏的牵强附会，\n其余生皆奉于黑岩厂与传授匠作之术，亦是不争的事实。\n\n在生涯与传说的最后，其人在华胥的天光中羽化而升，化作庇护工匠的星宿。\n但传说终究只是传说。筑成黑岩厂的既不是仙家秘术，也不是缥缈的云与风，\n而是一刀一锤的凿刻，是洒落岩间的汗水，是千百年间无数堪称平凡的工匠。\n毕竟贵金之神的契约从未规定过，凡人的决意无法胜过高居云端的仙家奇迹。\n\n「有云氏之巧，斫木为鸢，削竹为鹊，游飏三日而不集，是谓天下至工」\n「然则其世业，镌岩为坊，筑云为阁，贯天衡以成黑岩，故谓之利于民」\n「有云氏所言：何谓之巧？何谓之拙？利于民者谓之巧，余者皆谓之拙」"
  },
  "description": {
    "ru": "Экспериментальный вариант стандартного оружия, выкованный в кузнице Черногорья по поручению Нефритового Равновесия после того, как были изучены охранявшие обитель Тяньхэн древние механизмы.\n\n### История\nДревние говорили, что горы Тяньхэн богаты драгоценными камнями, а в глубинах Разлома кроются залежи нефрита. Земля тысячи камней издревле славилась своим богатством,\nа важнейшим местом добычи и переработки руды всегда считалась кузница Черногорья, которая находится в горах Тяньхэн.\n\nКузница Черногорья построена глубоко в горах. Она состоит из множества мастерских и плавильных печей, соединённых между собой почерневшими от копоти проходами.\nВ смутные времена, когда дикий огонь войны окрашивал землю алым, эти места служили убежищем для живущих поблизости горных племён.\nГоворят, здесь есть забытые ходы, которые ведут в древнее царство глубоко под землёй...\n\nВ «Сборнике каменных табличек» говорится, что тёмные ходы в горах когда-то проделал предок знаменитого в нынешнем Ли Юэ семейства Юнь.\nС той поры род Юнь вошёл в анналы истории как род кузнецов, а его основоположник на протяжении многих поколений остаётся покровителем мастеров и ремесленников.\n\nВ исторических источниках почти не осталось записей об этом человеке...\n«Предок Юнь был настолько искусен, что деревянные соколы и бамбуковые вороны, к которым он приложил руку, летали вокруг него три дня, не садясь на землю. Он достиг наивысшего мастерства».\n\nПервоначально изучение механики и постижение искусства ковки было неразрывно связано с Адептами.\nПоэтому основателя рода Юнь нередко считали учеником Адептов, а его способности приписывали дарам Адептов.\nВ самой известной истории о нём говорится, что во время смуты он сопровождал императора на войну.\nЗа свои воинские заслуги он получил признание трёх Адептов и был посвящён в тайны механики.\n\nГоворят, его способности были настолько чудесны, что он умел срывать облака с неба и возводить из них бесчисленные башни.\nИ даже из самого трухлявого и гнилого дерева он умел вырезать летающих птиц, которых было невозможно отличить от живых.\n«Черногорье выковано из облаков» - эту поговорку слышал каждый житель Ли Юэ.\nПоэты и сказители давно восхищаются контрастом этих двух образов.\nИ хотя легенда о башнях, выкованных из облаков, явно восходит к языковой игре (ведь фамилия «Юнь» имеет значение «облако»),\nтот факт, что основатель рода Юнь посвятил остаток своей жизни кузнице Черногорья и передаче секретов мастерства, остаётся неоспоримым.\n\nЛегенда гласит, что в конце жизни он вознёсся на небо и стал созвездием, оберегающим мастеров и ремесленников.\nНо в конечном счёте легенды это всего лишь легенды. Кузница Черногорья не соткана из облаков и ветра, да и секреты Адептов здесь ни при чём.\nОна была создана бесчисленными ударами зубил и молотков, выточена каплями пота самых обычных мастеров, которые тысячелетиями работали над её созданием.\nВ конце концов, в договоре с Золотым богом ничего не говорилось о том, что решимость смертных не способна превзойти чудеса бессмертных.\n\n«Предок Юнь был настолько искусен, что деревянные соколы и бамбуковые вороны, к которым он приложил руку, летали вокруг него три дня, не садясь на землю. Он достиг наивысшего мастерства».\nСкалы он превращал в мастерские, а облака - в высокие башни. В горах Тяньхэн он создал кузницу Черногорья. И посему говорят, что его труды принесли людям великую пользу.\nИ сказал Юнь: \"Какая работа зовётся мастерской? А какая неумелой? Работа, что идёт на пользу людям, зовётся мастерской. Всё прочее - работа неумелая\"».",
    "en": "A prototype for a standard-issue weapon the Yuheng commissioned from Blackcliff Forge after having analyzed the ancient mechanisms that protected the adeptal abode upon Tianheng.\n\n### Story\nThe ancients say that the mountains of Mt. Tianheng are filled with gems, and the depths of The Chasm are rich with jade. The nation of a thousand hills has long been known for its abundance,\nAnd its most critical mining and smelting facilities are located in Blackcliff Forge, carved into Mt. Tianheng itself.\n\nThe Forge was constructed by excavating the mountains, with countless workshops, furnaces, and connecting tunnels blasted black by dust.\nIn the tumultuous years when the fires of war dyed the land red, this place was also where the ancestors of the mountain tribes sought shelter.\nIt is even said that long-forgotten passages are within, tunnels to an ancient underground realm that lies in the deep places beneath the earth...\n\nAccording to the Stone Tablet Compilations, the first to carve the darkened paths through the mountains was the founder of the famous Yun family of Liyue.\nFrom that time hence, their clan, a house of smiths, has taken its place on the stage of history, regarded as honored progenitors by countless generations of artisans thereafter.\n\nAs for the stories of that person, the annals of history leave but a scant few lines—\n\"Such was Yun's ingenious craft that wood and bamboo might be carved into birds who would fly for three days without landing. Such were the works considered the apex of artisanry.\"\n\nThe study of mechanisms and the art of forging were all initially inextricably intertwined with the adepti.\nAs such, the founder was oft regarded as an apprentice of the adepti, and the techniques employed by said founder considered adepti teachings.\nThe tale most widely known today is that this personage once fought alongside Rex Lapis on campaign,\nAnd having accomplished much, was acknowledged by three adepti, one after the other, and was granted instruction in secret mechanical arts.\n\nLegend has it that these divine techniques were such that even clouds could be plucked from the skies with which manses might be molded,\nAnd even the rotting, wasting wood could be fashioned into moving birds and beasts, so alike to life as to confound the observing eye.\nAs such, the phrase \"The Blackcliff, forged from clouds\" has long been widely known in Liyue,\nAnd poets and storytellers have long delighted in the contrast between the two images.\nThough the legend of \"cloud-forging\" is a fanciful latter-day play on the family name \"Yun\" meaning \"cloud,\"\nNone dispute that the rest of the founder's life was dedicated to the Blackcliff Forge and the teaching of craftsmanship.\n\nAt life and legend's end, the founder ascended in heavenly light, becoming the guardian star of artisanry.\nStill, legends are naught but legends. It was no adeptal art that built the Forge, nor was it woven of whisps of wind and cloud.\nInstead, it was chiseled out one flake and one hammerstroke at a time, by the pouring sweat of countless ordinary artisans' brows over long centuries.\nDeus Auri's contract never stipulated that mortal resolve could never surpass adeptal miracles, after all.\n\n\"Such was Yun's ingenious craft that wood and bamboo might be carved into birds who would fly for three days without landing. Such were the works considered the apex of artisanry.\"\n\"Yet Yun's life and career were spent working rock into workshops, and molding clouds into manses. Thus was the Blackcliff forged in Tianheng, that the well-being of all the people might be served.\"\n\"For thus Yun said: What is clever? And what is clumsy? That which benefits the people is clever, and that which does otherwise is clumsy.\"",
    "zh": "解析昔日拱卫天衡的仙家机关后，由玉衡星委托黑岩厂锻造的实验型制式兵器。\n\n### 故事\n古语有云，天衡叠嶂连璧生，岩层渊薮玉辉蕴。千岩之国向来以富饶闻名于世，\n而其中最重要的矿藏产地与冶炼锻造之所，便是坐落于天衡山中的「黑岩厂」。\n\n「黑岩厂」乃是掘空山岳所建，无数工坊、熔炉与被尘灰灼得黢黑的甬道勾连，\n在纷乱的烽燧染红大地的年岁，此地亦被嶙峋岩山诸部族的先民用作避难之所。\n据说，其中有一些早已为世人所遗忘的古老甬道，甚至能通往大地深处的古国…\n\n据《石书辑录》所载，最初修凿山中黯道之人，正是如今璃月名门云家的开祖。\n作为锻造世家的云氏自此登上历史的戏台，其人亦被后世无数工匠尊奉为先师。\n\n至于其人的记载，青史中不过寥寥数行——\n「有云氏之巧，斫木为鸢，削竹为鹊，游飏三日而不集，是谓天下至工」\n\n无论是机关之学还是锻造之术，最初都与仙家密不可分，\n正因如此，其人常被视作仙家学徒，其技亦被称作仙授。\n根据今人广知的说法，其曾于天纪俶扰之时随帝君征战，\n树功立业，先后蒙受三位仙君赏识，获赐机关秘术之教。\n\n传说其技法之神妙足以将高天之云摘下，筑成无数楼阁，\n亦能将最为劣质的朽木錾作奔走的鸟兽，令人难辨真伪。\n所谓「黑岩筑于云」的说法，如今在璃月早已广为人知，\n二者在意象上的冲突，也向来为诗家与说书人津津乐道。\n尽管「筑云」的传说不过是后世基于其姓氏的牵强附会，\n其余生皆奉于黑岩厂与传授匠作之术，亦是不争的事实。\n\n在生涯与传说的最后，其人在华胥的天光中羽化而升，化作庇护工匠的星宿。\n但传说终究只是传说。筑成黑岩厂的既不是仙家秘术，也不是缥缈的云与风，\n而是一刀一锤的凿刻，是洒落岩间的汗水，是千百年间无数堪称平凡的工匠。\n毕竟贵金之神的契约从未规定过，凡人的决意无法胜过高居云端的仙家奇迹。\n\n「有云氏之巧，斫木为鸢，削竹为鹊，游飏三日而不集，是谓天下至工」\n「然则其世业，镌岩为坊，筑云为阁，贯天衡以成黑岩，故谓之利于民」\n「有云氏所言：何谓之巧？何谓之拙？利于民者谓之巧，余者皆谓之拙」"
  },
  "notes": {
    "general": "",
    "byVolume": {}
  },
  "weapon_type": "bow",
  "type": "bow"
}