{
  "id": "mika",
  "category": "stories",
  "icon": "assets/icons/stories/character/mika.webp",
  "title": {
    "ru": "Мика",
    "en": "Mika",
    "zh": "米卡"
  },
  "region": "Мондштадт",
  "rarity": 4,
  "game_version": "3.5",
  "tags": [],
  "languages": [
    "ru",
    "en",
    "zh"
  ],
  "text": {
    "ru": "### О персонаже\n\nПоявившись в штабе Ордо Фавониус, Мика старается как можно скорее обсудить все рабочие вопросы и незаметно уйти, чтобы не мешать работе других рыцарей ордена. Мика всегда нервничает, если с ним заводят разговор на посторонние темы, и в панике убегает сразу после того, как вежливо свернёт беседу. Рыцари знают, что этого молодого человека зовут Мика, что он младший брат Хоффмана, второй сын семьи Шмидт, а сейчас - один из членов разведывательного отряда. Но они не имеют понятия, какой работой занят Мика, и даже не знают, что новой версией военной карты орден полностью обязан Мике. В новой карте содержатся подробные данные по рельефу местности в Мондштадте и его окрестностях, снабжённые удобными примечаниями: состояние дорог, возможное скопление монстров, возвышенности, подходящие для обороны, типы природных ресурсов и их распределение... Карта составлена настолько подробно, что при взгляде на неё разбегаются глаза. Это результат двухлетних изысканий Мики, когда он исходил весь Мондштадт вдоль и поперёк. Некоторые рыцари, сражавшиеся бок о бок с Микой, знают, что он прекрасно владеет копьём и арбалетом, его уникальный стиль ведения боя оставляет неизгладимое впечатление. Но после настойчивых просьб Мики они стараются поменьше распространяться о его умениях.\n\n«Мика боится лишнего внимания. Простой взгляд в глаза может заставить его нервничать, а если вы начнёте расточать комплименты, Мика под землю провалится от неловкости. Он много нам помогал - само собой, мы должны заботиться о его чувствах!»\n\n### История персонажа 1\n\nМика вырос в любящей семье. Его мать - писательница, отец - отставной рыцарь Ордо Фавониус, а старший брат Хоффман - действующий член рыцарского ордена. Когда Мика едва выучился читать, его мать отправилась путешествовать в поисках материала для новой книги, а отец её сопровождал. Присматривать за Микой пришлось Хоффману. Но днём Хоффман был занят службой, а по ночам пьянствовал со своими друзьями из ордена. Его собственная жизнь напоминала бардак, так что о Мике он позаботиться толком не мог. Зато маленький Мика научился заботиться и о себе, и о старшем брате, когда тот за полночь приходил пьяным домой. Пока сверстники Мики резвились и играли, он научился управляться с хозяйством, наладил режим, готовил Хоффману еду, приводил в порядок его одежду. Каждую неделю родители Мики отправляли с нарочным письмо в Мондштадт, чтобы дети за них не волновались. Мать Мики превосходно владела словом, её описания пейзажей читались увлекательно, словно сказки. Мика любил читать письма родителей, а потом отмечать их местоположение на карте и прочерчивать маршрут. Он мог часами представлять себе захватывающие приключения родителей в дороге. Постепенно Мика полюбил рассматривать карты, даже выучил наизусть топографию некоторых районов. Но Хоффману пришлось его разочаровать: «Карта Мондштадта, которую оставили родители, давно устарела. Она всегда была не особенно точной, так что вся твоя работа пропала даром». Впрочем, это было ожидаемо. В конце концов, смельчаки, способные исследовать дикие местности, обычно становились искателями приключений, для которых поручения и мора превыше всего. А карты - что карты? Обойдёмся теми, что есть. Опытные картографы зачастую не обладали боевыми навыками, позволяющими отправиться в дикую местность, и не могли себе позволить нанять телохранителей. Возможно, когда-нибудь у рыцарского ордена будет достаточно средств, чтобы пригласить хорошего картографа и обновить карту. Но пока в Мондштадте царили мир и благодать, этот план казался несбыточным. Маленький Мика погрузился в раздумья: «Если бы я мог отправиться в путешествие, как папа и мама... Обойти весь мир и составить подробную карту... лучшего желать нельзя». С тех пор у Мики появилась ясная цель в жизни: «Я стану специалистом по картографии».\n\n### История персонажа 2\n\nВернувшись в Мондштадт и узнав о цели, которую поставил перед собой Мика, родители очень обрадовались и пообещали, что во всём его поддержат. С того дня Мика стал проводить много времени в библиотеке, изучая книги по географии Тейвата и упражняясь в картографировании. Воспитанный, одарённый и трудолюбивый мальчик произвёл хорошее впечатление на Лизу, поэтому она много помогала Мике в поиске толковых книг, чтобы он не тратил время на устаревшие тома. Мика долго сидел над книгами, и в конце концов Лиза была вынуждена признать: «Твоих нынешних знаний хватит даже для поступления в Академию». Тогда Мика стал искать способы применить свои знания на практике. И как раз тогда Элла Маск, с которой он познакомился в библиотеке, искала проводника, чтобы отправиться в отдалённый район и пообщаться с хиличурлами. Так Мика получил своё первое задание. Им удалось добраться до места, но хиличурлы недопоняли, что они хотят сказать, разозлились и крепко их избили... Мика пришёл к выводу, что это произошло, потому что он совсем не умеет сражаться.\n\n«Пока я не умею за себя постоять, я никогда не смогу свободно исследовать неизведанные территории».\n\nПосле того случая Мика стал брать у Хоффмана уроки боевых искусств с тем же усердием, с каким раньше изучал картографию. К счастью, ему повезло с природными данными, и он быстро усвоил основы. По случайному совпадению, в ордене тогда как раз готовили план экспедиции, которая должна была состояться три года спустя. Оставалось ещё несколько вакансий, в том числе должность передового геодезиста. Требования к кандидату были очень строги: он должен был разбираться в картографии, а поскольку экспедиция планировалась в довольно опасном районе, ещё ему следовало уметь работать на передовой и обладать необходимыми боевыми навыками, чтобы сражаться с монстрами. Мика понимал, что это его шанс, о такой возможности он не мог даже мечтать... Вообще-то он думал, что однажды присоединится к ордену в качестве приглашённого консультанта. Теперь же оказалось, что ордену нужен свой картограф, полноправный член экспедиции, который будет работать на передовой. Сначала Мика сомневался в себе. Он боялся, что не достоин такой важной роли, ведь передовым геодезистом Ордо Фавониус может быть «только лучший из лучших». Поддержка отца и брата помогла ему одолеть сомнения, и он до сих пор помнит их слова: «Не требуй от себя слишком многого, самое главное - ты можешь быть полезен ордену, этого достаточно». «Большинство рыцарей - обычные люди, как ты и я. Но из обычных людей может собраться блестящий отряд, который ничем не уступит отряду сильнейших искателей приключений». Так что Мика рискнул и подал заявку на вакансию Ордо Фавониус. При мысли о том, что он сможет заниматься на работе любимым делом, страх отступал.\n\n### История персонажа 3\n\nНовость о том, что Мика откликнулся на вакансию передового геодезиста, быстро разошлась среди рыцарей Ордо Фавониус.\n\n«Младший брат Хоффмана тоже хочет стать рыцарем! Маленький Мика, который всегда заботился о своём пьяном брате, хочет к нам присоединиться!»\n\nЗастенчивый Мика никогда не думал, что окажется в центре внимания, он с трудом дышал, сердце бешено стучало. Мика боялся провалить отбор и опозорить отца, разрушить карьеру брата, испортить репутацию семьи. Поскольку многие члены семьи Шмидт состояли в рыцарском ордене, комиссия решила усложнить испытания для кандидатов и сделать процесс отбора публичным, чтобы избежать возможной предвзятости. С учётом требований, предъявляемых к геодезисту на передовой, Кэйа придумал целый ряд суровых испытаний, призванных строго оценить способности участников:\n\n- на время добраться по пресечённой местности до середины Драконьего хребта в доспехах, с тяжёлым грузом и ограниченным провиантом;\n\n- изучить местность, кишащую монстрами, и составить для неё новую карту без помощи справочных материалов;\n\nК счастью, Мика был хорошо готов, он старался как мог и прошёл отбор в тройке первых. Двум другим кандидатам, которые прошли отбор вместе с ним, Мика тоже помогал во время испытаний, потому что считал их не конкурентами, а будущими товарищами. Магистру Варке очень понравился новичок, который так здорово умеет работать в команде. Одного из прошедших отбор кандидатов перевели в отряд кавалерии, другого - в исследовательскую команду, а Мика отправился в экспедицию с магистром Варкой. С тех пор Варка каждую неделю учил Мику технике ведения боя и давал ему много «домашних заданий». Позднее Мика вступил в разведывательный отряд. Взаимодействие с капитаном отряда, которая отличается весьма странным характером, помогло Мике приобрести необходимые навыки общения и быстрее адаптироваться к работе в элитном разведывательном отряде. После вступления в рыцари Мика оттачивал технику картографирования, работая геодезистом на передовой и разведывая опасные места. Вместе с этим под руководством Варки он постоянно улучшал и другие свои навыки. Трудолюбивый новобранец постепенно окреп и сам не заметил, как превратился в серьёзного и надёжного рыцаря.\n\n### История персонажа 4\n\nМика неустанно совершенствовал свои навыки в реальном бою, благодаря чему менее чем за два года стал ключевым членом разведывательного отряда и выполнил бесчисленное количество заданий вместе со своими товарищами. Запланированная дата приближалась, и экспедиция вскоре должна была отправиться в путь. На прощальном вечере магистр ордена Варка был приятно удивлён, увидев новенький блестящий Глаз Бога на правой руке Мики. Однако после того, как он пригласил Мику на спарринг, магистр заключил, что его уровень способностей «поразительный, но недостаточно высокий». Мика не понимал, что это значит, пока экспедиция не вошла в опасную запретную зону, где он собственными глазами увидел монстров, которых магистр ордена Варка использовал в качестве эталона при оценке своих способностей. Это были неподдающиеся описанию, блуждающие существа, которые превращались в кошмар для любого незадачливого рыцаря, отставшего от отряда. Скорость движения авангарда определяла скорость движения всего отряда, поэтому в наиболее напряжённые дни Мика мог отдыхать не более получаса в день. Он впервые работал в таких условиях, и ему было непросто. Не говоря уже о том, что помимо неведомых опасностей, экспедиция находилась под пристальным вниманием другой стороны... Однажды, когда Мика готовился ко сну, он получил предупреждение от другого разведчика, что рыцари встретились с врагом. Когда Мика примчался на место, Варка уже сформировал боевой строй из своих верных подчинённых. В кромешной тьме ночи Мика смутно различал шеренгу солдат, безмолвно стоявших, словно безжизненные боевые механизмы. А прямо в центре вражеского строя возвышался тёмный силуэт. Факелы освещали местность, но Мика не мог разглядеть ничего, кроме жутких тёмно-синих глаз, которые, казалось, светились неведомым светом. Благодаря подсказке своего товарища по отряду, Мика узнал, что это был Предвестник Фатуи Капитано и его подчинённые. Оказалось, что рыцари Ордо Фавониус столкнулись с аванпостом Фатуи. Обе стороны не желали уступать и постоянно запрашивали подкрепления, в итоге дойдя до высшего командования. Мика чувствовал, как нарастает напряжение, как от предчувствия конфликта немеют конечности. Он мысленно представлял, как противостояние перерастает в вооружённый конфликт, и что нужно делать, если это произойдёт... Особенно это касалось Предвестника - Мика знал, что он будет абсолютно беспомощен... Путаница в голове и сильная усталость мешали сосредоточиться. Варка, в свою очередь, выглядел совершенно невозмутимым. Он издалека поприветствовал Предвестника и направился к нему с оружием в руках. Капитано тоже подал сигнал своим людям приготовиться, а сам начал медленно приближаться. Когда напряжение достигло пика, Варка и Капитано обменялись короткими фразами и, похоже, пришли к соглашению. Тёмный силуэт поднял руку, призрачные тени солдат Фатуи молча повернулись и безмолвно ушли вместе с ним. Все рыцари вздохнули с облегчением, но некоторые продолжали дрожать от страха. Когда Варка вернулся, он выглядел спокойным, как всегда:\n\n«Какая удивительная встреча! Если бы не особые обстоятельства, я бы с удовольствием вызвал его на дуэль!»\n\n«Он вовсе не глупец и прекрасно понимает, что вооружённое столкновение на чужой территории не сулит ничего хорошего обеим сторонам».\n\nТолько тогда Мика понял, что находился на грани боевого столкновения, но магистр ордена предотвратил конфликт. Как властное присутствие Капитано, так и невозмутимое спокойствие, с которым магистр ордена урегулировал кризис, произвели глубокое впечатление на Мику. Он долго размышлял об этом и пришёл к выводу, что, несмотря на то, что его сила росла, ему ещё предстоит пройти долгий путь, чтобы научиться правильно действовать в подобных ситуациях. Недостаточно просто делать всё возможное, чтобы помочь отряду. Он должен трудиться ещё усерднее и стать достаточно опытным, чтобы справляться с самыми разными обстоятельствами...\n\n### История персонажа 5\n\nК счастью, Мике не довелось столкнуться с чем-то слишком опасным, и он без особых трудностей преодолел сложный период. Во время Праздника вина он вернулся в Мондштадт с письмом от магистра ордена Варки и занял свою прежнюю должность в разведывательном отряде. Члены отряда были рады его возвращению и одновременно удивлены поразительным прогрессом, которого он добился, ведь он мог теперь легко выполнять задания, для которых обычно требовалось три разведчика. А если учесть, что в письме магистра ордена вскользь упоминались Фатуи, и что Мика был ключевым участником экспедиции под непосредственным командованием Варки... Его товарищи по отряду быстро связали эти два момента, и возникла странная логическая цепочка:\n\n«Мика противостоял Фатуи! Мика способен сражаться с элитными бойцами Фатуи! Мика сражался вместе с магистром ордена и одержал победу над Предвестником Фатуи!»\n\n«Иначе как он мог вдруг стать таким сильным? Мика - наш герой! Его можно просить о чём угодно - он всё для нас сделает!»\n\nПравда заключалась в том, что опыт Мики в экспедиции сыграл роль тренировки. Другие рыцари тоже в той или иной степени добились успехов, только они ещё не вернулись, поэтому Мику не с кем было сравнивать. Мика не знал, как относиться ко всем этим несуразным слухам, поэтому он обратился за советом к Джинн и Кэйе. Джинн уведомила командиров каждого отряда о необходимости придерживаться рационального подхода и воздерживаться от распространения домыслов, основанных исключительно на слухах. Кроме того, произошедшие во время экспедиции события считаются строго конфиденциальными, и к ним следует относиться с осторожностью. Кэйа, напротив, с удовольствием подшучивал на эту тему. Рыцари Ордо Фавониус в той или иной степени испытывали неприязнь к Фатуи, и слух о том, что «Мика хорошенько им наподдал», вполне мог поднять боевой дух. По крайней мере, Мика чувствовал себя спокойнее, зная, что действующий магистр в курсе произошедшего и знает, что он не собирался создавать неприятности. Он, как обычно, ходил на службу и делал всё возможное, чтобы помочь другим. Однако слухи на этом не прекратились, и Мика не раз попадал в неловкие ситуации. Всё больше и больше рыцарей подходили к нему, чтобы попросить новые карты, помочь с обслуживанием оружия или поделиться пайком. Казалось, все разделяли бездумную веру в то, что, проводя больше времени с Микой, они смогут стать такими же сильными, как он.\n\n### Передовое картографическое устройство\n\nЗамысловатое устройство в форме книги, которое Мика повсюду носит с собой. Оно было разработано Микой и техническими специалистами из исследовательской команды, а его ключевые компоненты изготовлены с использованием последних алхимических разработок Альбедо. В устройство встроен блокнот, созданный для быстрого создания и использования карт. Каждый из его листов можно легко вынимать и заменять. Сзади на устройстве вырезан сложный узор. Направление элементальной силы на узор активирует ромбовидный компонент на передней стороне устройства, который, в свою очередь, испускает волновой луч в форме веера в направлении цели. Расстояние между устройством и целью можно точно рассчитать, используя время, необходимое для отражения луча. Увеличивая частоту и амплитуду волнового луча, устройство создаст карту небольшого участка местности. Все эти функции значительно повышают точность карты, но, к сожалению, всё остальное, включая статистическую информацию и расчёты для конкретной местности, пользователь должен вычислить самостоятельно в уме. Только те, кто обладает отличными навыками пространственного мышления и обширными знаниями местности, способны в полной мере использовать эту функцию. Таким образом, Мика является единственным геодезистом, который может без труда работать с устройством, хотя использует его довольно редко. Были и другие импровизированные устройства, которые планировалось раздать другим командам, но в настоящее время они служат для снабжения запасными частями устройства Мики. Прибор был создан как верный помощник Мики и символ признания его лучшим геодезистом, но Мика никогда не рассказывал о его впечатляющих возможностях другим. Для Мики это выглядит как хвастовство, не говоря уже о том, что это может добавить работы Альбедо... А беспокоить других было последним, чего Мика хочет.\n\n### Глаз Бога\n\nОднажды Мика оказался на грани жизни и смерти. Это случилось вскоре после того, как он присоединился к разведывательному отряду. Информация об одном участке устарела, и Мика взял на себя труд уточнить детали местности. Он осторожно пробирался по руинам, когда нечаянно задел кусок камня от разрушенной стены, чем привлёк внимание двух магов Бездны, притаившихся в темноте. Когда языки пламени переплелись, его мгновенно охватил прилив элементальной силы, словно она собиралась искрошить его на куски и превратить в обед для монстров. Боль и паника заполнили его, а в сознании осталась только одна мысль - нужно бежать и предупредить других.\n\n«Эти монстры... Они представляют угрозу даже для самых опытных членов экспедиции...»\n\nВ обязанности фронтового геодезиста входило уберечь своих соратников от опасных ситуаций, подобных этой. Маги Бездны закричали от радости и уже собирались приказать другим монстрам выйти из укрытия, когда завесу пламени разорвало вращающееся копье. По руинам поплыл ледяной туман, мгновенно разогнав невыносимую жару. Когда маги Бездны, наконец, разобрались в ситуации, Мика уже скрылся вдали, продолжая извиняться достаточно громко, чтобы монстры услышали: «Простите! В следующий раз я обязательно постучу, прежде чем войти. Тогда мои старшие товарищи смогут сразиться с вами в честном бою!» «Следующий раз» наступил очень быстро - основные силы разведывательного отряда получили сообщение о монстрах и быстро, но осторожно устранили угрозу. Они с удивлением обнаружили, что щиты обоих магов Бездны были сильно повреждены, а, взглянув на сияние, исходящее от Глаза Бога на правой руке Мики, они всё поняли... В тот день ужин в разведывательном отряде был особенно роскошным. Все поднимали бокалы в честь торжества, а сам Мика, казалось, пребывал в шоковом состоянии и был не в состоянии осознать происходящее.",
    "en": "### Character Details\n\nWhenever he shows up at the Knights of Favonius headquarters, Mika always swiftly finishes any discussions to be had with his fellow knights, then quietly slips away to avoid becoming a hindrance to others' work.\nMika always gets nervous when someone strikes up a conversation with him, frantically scampering away right after politely putting an end to the idle chatter.\n\nThe knights know that the young man's name is Mika, and that he is Huffman's younger brother and the second son of the Schmidt family. They also know that he is a member of the Reconnaissance Company, but nothing much beyond that.\n\nFew are aware of what Mika's job entails, nor do they know that the widely-promoted, updated version of their military map is the fruit of his labors.\n\nThe new map consists of detailed statistical data regarding almost every corner of Mondstadt with practical markers indicating road conditions, areas with heightened monster activity, high ground that can serve as temporary strongholds, and the distribution of natural resources... The amount of detail could almost make your head spin.\n\nAll of this is the result of Mika's own labor throughout the two years he has spent traveling all across Mondstadt and investigating every inch of terrain he set foot on.\n\nKnights who have fought alongside Mika know that he finds using both lance and crossbow at the same time the most convenient, and his unique fighting style has left a lasting impression.\n\nHowever, they have also been solemnly \"warned\" by Mika to never speak of him to others unless absolutely necessary.\n\n\"Mika's terrified of drawing the attention of others — he'll get nervous if you so much as stare at him, to say nothing of showering him with compliments. He's been a great asset to the Knights and helped us out a lot, so respecting his boundaries is the least we can do as seniors!\"\n\n### Character Story 1\n\nMika comes from a loving family. His mother works as an author writing about local conditions, his father is a retired Knight of Favonius, and his older brother Huffman is a current member in the Knights' ranks.\n\nWhen Mika began learning to read, his mother went inspiration-gathering abroad with his father accompanying her. During that time, the responsibility of looking after little Mika landed in Huffman's hands.\n\nHowever, Huffman had already made the Knights of Favonius his second home — he was preoccupied with work during the day and indulged in drinking with his friends night after night. With his own life lacking organization, how was he expected to take care of his little brother?\n\nSo it was little Mika who learned to take care of both himself and his brother whenever he'd return home drunk at night. When other children his age were enjoying their childhood without a care, Mika had already learned to stick to an organized schedule, sometimes even helping Huffman with his everyday chores.\n\nWhile they were away, Mika's parents always made sure to send a letter back to Mondstadt every week to keep their children from worrying. Mika's mother, being an excellent writer, could somehow describe the scenery she's seen in a mesmerizing way akin to fairytales. Mika loved to read his parents' letters before looking for their exact location and marking out their travel route on a map. Picturing his parents' wonderful adventures was Mika's favorite pastime.\n\nBefore long, Mika developed a passion for reading maps, and even committed the terrain of many locations to memory.\n\nUnfortunately, Huffman had to ruin the mood when he broke the bad news to Mika: \"I'm afraid your efforts have been wasted on the map Mom and Dad left us. It's very outdated, and it wasn't very accurately drawn in the first place.\" But that was to be expected. After all, those who with the ability freely explore the wilderness would likely have all become adventurers with nothing but commissions and Mora on their minds. To them, just about any map would do.\n\nOn the other hand, most of those who knew how to draw decent maps were not skilled in combat, so it would be much too dangerous for them to survey the wilderness themselves. Not to mention their limited income, which wouldn't allow them to afford bodyguards. Perhaps the time would come when the Knights of Favonius finally had sufficient budget to hire experts to deal with matters like these, but with Mondstadt as peaceful as one could hope for, no one knew for sure when something as trivial as cartography could be put on the schedule. So little Mika thought to himself: If he could reach every corner of the world just like his parents, and record every detail of the terrain beneath his feet... That would be the most fun ever.\n\nFrom then on, Mika set a clear goal for himself.\n\n\"I'll become Mondstadt's expert cartographer.\"\n\n### Character Story 2\n\nWhen Mika's parents returned to Mondstadt, they were delighted to hear of Mika's new-found goal and promised to do whatever they could to support him.\n\nFrom that day on, Mika dedicated most of his time to poring over geography books and assiduously honing his drawing skills in the library.\n\nLisa took a liking to this polite, gifted yet hardworking child and often recommended books to him, guiding him towards the most efficient path.\n\nAfter some time, Mika gained Lisa's recognition — \"With your current skills and abilities, you just might qualify for studying at the Akademiya.\"\n\nIt was then that Mika began looking for opportunities to put his knowledge to the test. As it happens, Ella Musk, whom he had gotten acquainted with while studying at the library, happened to be looking for a guide for a language exchange trip to the secluded wilderness.\n\nAnd that became Mika's first real expedition. Though they did safely arrive at their destination, due to an error in Ella Musk's word choice, the pair ended up getting beaten by the hilichurls.\n\nMika concluded that this setback was due to his lack of combat prowess. \"I need to learn how to protect myself,\" he thought, \"or I won't be able to guarantee the success of my expeditions to unfamiliar areas.\"\n\nThereafter, Mika rode the momentum from his time spent learning in the library and began to learn fighting techniques from his brother. Luckily, Mika had a strong constitution and quickly grasped the basics.\n\nIt happened that the Knights of Favonius had just drafted their plan for an expedition set to depart three years later. They were still looking to recruit a few more members to fill some positions, and \"Front-Line Surveyor\" was among the open spots.\n\nThis role had strict prerequisites: those applying for the position should have some level of expertise in cartography, and due to potentially dangerous conditions, they would be leading the team from the front lines, making combat skills a must.\n\nThis was Mika's chance, but it all felt too much like a dream...\n\nMika initially believed that he would be invited into the team as an external consultant, but the position of Front-Line Surveyor would no doubt make him a full-fledged member of the expedition — and one crucial to the entire team. He was daunted by the thought at first, afraid that he wasn't worthy of such an important role that according to him, \"only the strongest would qualify for.\"\n\nHis doubts were soon dispelled by his father and brother's encouragement, and he remembers their words to this day:\n\n\"You don't have to ask too much of yourself. Doing your best to help will be more than enough.\"\n\n\"Most of the knights are just ordinary people like us, but once we put our strengths together as a team, even the strongest of adventurers would struggle to prove our equal.\"\n\nThus, Mika seized the opportunity and signed up for the position.\n\nHe felt reassured that he would, at least, be dedicating his time to what he loved.\n\n### Character Story 3\n\nWord of Mika signing up for the expedition spread like wildfire throughout the Knights of Favonius.\n\n\"Huffman's little brother will be joining us! The little kid who always takes care of that drunkard will be joining the Knights!\"\n\nThe anxiety from unexpectedly becoming the center of attention made his breaths quicken as his heart pounded — Mika was afraid of failing the Knights' assessment and disgracing his father, ruining his brother's career, or worse, ruining the reputation of his family name.\n\nConsidering that many members of the Schmidt family had already joined their ranks, the Knights of Favonius decided to raise the bar for entry and make the whole assessment process public in order to make the selection as fair as possible.\n\nTaking real-life scenarios into consideration, lead examiner Kaeya came up with a series of challenges that strictly assessed the participants' abilities:\n\nHiking up Dragonspine while wearing full armor and carrying a heavy load;\n\nMapping out a monster-infested region without the aid of any reference material...\n\nLuckily, Mika came well-prepared and gave it his all, eventually passing the most difficult challenge and becoming one of three successful candidates.\n\nThe other two candidates had both received Mika's aid along the way as well — to him, they were more like future teammates than competitors, in any case.\n\nMika's excellent exhibition of teamwork gained the recognition of Grand Master Varka, who allocated the two other new recruits to the Cavalry Company and Investigation Team, while personally taking Mika in to go with him on his expedition.\n\nEvery week, Varka would teach Mika combat techniques and give him assorted \"homework\" to complete.\n\nMika would later join the Reconnaissance Company. Communicating with its rather unusual Captain further strengthened his communication skills, which would help him greatly when working with the elite knights of the expedition team.\n\nAfter joining the Knights, Mika honed his cartography skills while investigating dangerous locations as a Front-Line Surveyor while receiving pointers on how he might improve his other skills from Varka.\n\nThe diligent young recruit quickly became a calm and reliable knight — though it seems as though he has yet to realize that himself.\n\n### Character Story 4\n\nAs Mika continuously refined his skills in real-life combat, he became a core member of the Reconnaissance Company in less than two years, completing countless missions alongside his teammates.\n\nThe scheduled date drew near, and the expedition team was soon about to depart.\n\nAt the send-off party, Grand Master Varka was pleasantly surprised by the shiny new Vision on Mika's right wrist. But after personally inviting Mika to spar, he concluded that Mika's current abilities were \"remarkable, but far from enough.\"\n\nMika didn't figure out what that meant until the expedition team entered a dangerous restricted area, where he finally saw with his own eyes the monsters Grand Master Varka had used as a reference when judging his powers.\n\nThose unnamable, wandering creatures could become a nightmare for any knight unfortunate enough to stray away from the team.\n\nThe speed of their scouts in the vanguard determined how fast the whole expedition team proceeded, so during the days when the team was the busiest, Mika could only rest for half an hour a day.\n\nIt was Mika's first time working under such high pressure, and he did so with great difficulty. Not to mention that apart from dangers of the unknown, the expedition team was under the watchful gaze of another party...\n\nOne day, when Mika was getting ready to call it a night, he received a warning from another scout that the Knights had encountered enemies.\n\nWhen Mika hurried on scene, Varka had already drawn up battle lines with his trusty subordinates.\n\nIn the depths of the pitch-dark night, Mika could vaguely make out a line of soldiers, silently standing there as if they were lifeless war machines.\n\nAnd right in the middle of the enemy formation was a dark, distinct silhouette. Even though torches lit the area, Mika could see nothing but their eerily dark blue eyes that seemed to glow with an uncanny aura.\n\nAt his teammate's reminder, Mika learned of their identity — the Fatui Harbinger known as \"The Captain\" and his direct, elite subordinates.\n\nAs it turned out, their vanguard had bumped into Fatui scouts and an altercation had ensued, resulting in both sides getting jumpy and continuously requesting reinforcements, eventually alerting their respective commanders.\n\nThe scent of gunpowder was thick in the air, the sense of crisis turned Mika's limbs numb and cold.\n\nHe couldn't help visualizing the confrontation escalating into an armed conflict, and what he should do if such a thing were to happen...\n\nThe Harbinger, in particular — Mika knew that he would be utterly helpless to parry a single half-hearted swipe from this person.\n\nHis jumbled thoughts and exhaustion made it difficult to breathe or focus.\n\nVarka, however, seemed completely unfazed. He greeted the Harbinger from afar and walked towards him with his weapon in hand. The Captain, too, signaled his men to stand by as he began slowly stepping forward.\n\nAs the tension between the two parties reached its peak, Varka and The Captain briefly conversed and seemed to reach an agreement.\n\nThe dark silhouette raised his arm, and the ghostly shadows of the Fatui soldiers silently turned and departed with him.\n\nThe Knights all heaved a sigh of relief, and some were even trembling with fear. But when Varka returned to the Knights' formation, he looked as relaxed as ever.\n\n\"Well, that was a surprise! If it weren't for our unique circumstances, I would've loved to invite him for a duel!\"\n\n\"And it's not like he's a stubborn fellow. He's well aware that engaging in battle in a strange and foreign land would've been disadvantageous for both of us.\"\n\nIt was until then that Mika realized they had been on the precipice of war, and conflict had been avoided only because the Grand Master had been there to prevent it.\n\nThe Captain's overpowering presence and the calmness with which Grand Master Varka handled the crisis both left a profound impression in Mika's mind.\n\nMika reflected on this experience for a long time and concluded that although he had been improving in strength, he still had a long way to go when it came to dealing with situations like that.\n\nThere was more to be done than just doing his best to help the team. He had to work harder to become a reliable Knight who could handle all manner of incidents...\n\n### Character Story 5\n\nFortunately, Mika would not run into anything exceedingly dangerous during the expedition and smoothly made it past that most difficult period.\n\nDuring Mondstadt's Weinlesefest, Mika returned to Mondstadt with Grand Master Varka's letter and resumed his post in the Reconnaissance Company.\n\nThe members of the Reconnaissance Company were both excited at his return and surprised at the astonishing progress he had made — for he could now easily complete tasks that usually required three forward scouts.\n\nAnd considering that the Grand Master's letter had vaguely mentioned the Fatui, and that Mika had been a key member on the expedition under Varka's direct command... His teammates quickly connected the dots and a strange chain of logic emerged:\n\n\"Mika fought against the Fatui! Mika might've fought against Fatui elites! Mika must've fought alongside the Grand Master and won a battle against a Fatui Harbinger!\"\n\n\"How else could he have become this strong all of a sudden? Mika's our hero! He can now do anything for us!\"\n\nTruth be told, Mika had simply accrued a great deal of experience — the other Knights who had gone had also made progress to varying extents. They simply had yet to return, and thus no valid comparison could be made.\n\nMika didn't know how to deal with all the absurd rumors, and so he consulted Jean and Kaeya for advice.\n\nJean informed the leader of each company to remain rational and refrain from spreading rumors based purely on speculation. Besides, many matters regarding the expedition were considered highly confidential and should be treated with discretion.\n\nKaeya, on the other hand, seemed to enjoy joking about the rumors. Members of the Knights of Favonius all more or less held some sort of dislike for the Fatui, and a rumor that says \"Mika gave the Fatui a good beating\" could very well boost morale.\n\nWhatever the case, Mika felt greatly reassured now that the Acting Grand Master had been made aware of the situation and was comforted to know that he hadn't caused any trouble for anyone.\n\nHe reported to duty as usual and made sure he did all he could to help others.\n\nBut the exaggerated rumors couldn't be un-spread, and Mika has found that gaining too much trust comes with its own fair share of difficulties...\n\nRecently, more Knights have been coming up to him to borrow a new map, ask for help maintaining a weapon, or request a share of the Reconnaissance Company's field rations.\n\nAll of them seem to hope that some of his powers might rub off on them so that they can become stronger quickly, just like him.\n\n### Multipurpose Front-Line Surveying Device\n\nAn intricate book-shaped device Mika carries with him wherever he goes.\n\nIt was developed by Mika and technicians from the Investigation Team, and its key components were made using Albedo's latest alchemical creations.\n\nA notebook is embedded in the device's interior that can be used to record information. Designed to facilitate the quick production and use of maps, each of its pages can be conveniently removed and replaced.\n\nAn elaborate pattern is carved on to the back panel of the device. Channeling elemental power into the carving will activate the prism-shaped component outside said panel, which will in turn fire a \"wavebeam\" towards a fan-shaped target region.\n\nThe distance between the device and the target region can then be accurately calculated using the time taken for the beam to bounce back. By increasing both the frequency and amplitude of the beam, the device will generate a sketch of a small area of terrain.\n\nThis function can greatly improve the accuracy of a map, but regrettably, everything else — including the statistical information and calculations regarding the terrain in question — has to be computed in the user's mind.\n\nOnly those with excellent spatial reasoning skills and an extensive knowledge of the target terrain are capable of making full use of this function.\n\nThus, Mika became the only Front-Line Surveyor who could use the device without difficulty, and its overall usage rate is not very high.\n\nThere had been other improved devices originally planned for distribution to other teams, but they have been put into storage, to be used as spare parts for Mika's device.\n\nThe device is Mika's trustiest helper in his work and a symbol of honor for being the best surveyor, but Mika has never once mentioned its impressive features to others.\n\nTo Mika, that feels too much like bragging, not to mention that it could potentially give Albedo extra work... Troubling others is the last thing Mika ever wants, after all.\n\n### Vision\n\nMika was once in a life-or-death situation.\n\nThis was not long after he joined the Reconnaissance Company — the information on a certain area was no longer valid, and Mika had taken up the task to update the details of its terrain on his own.\n\nHe slowly crept into the ruins, only to accidentally knock off a piece of stone from the broken wall, alerting two Abyss Mages lurking in the dark.\n\nAs the flames intertwined, a rush of elemental power instantly engulfed him as if it was about to crush him into pieces and turn him into the monsters' next meal.\n\nPain and panic flooded his senses, and only one thought remained in his consciousness — he needed to escape and warn others.\n\n\"These monsters... They'd be a threat to even the most experienced members in the company...!\"\n\nIt was the responsibility of a front-line land surveyor to keep their teammates from dangerous situations like this.\n\nThe Abyss Mages shrieked in glee and were about to command other monsters to come out of hiding when a spinning spear tore the curtain of flames apart. An icy mist burst across the ruins, clearing the unbearable heat in an instant.\n\nWhen the Abyss Mages finally made sense of the situation, Mika had already fled far away, though still apologizing loudly enough for the monsters to hear:\n\n\"I'm sorry! I'll remember to knock before entering next time. That way, my seniors can fight you fair and square!\"\n\n\"Next time\" soon came — the Reconnaissance Company's main force were notified of the monsters and swiftly but cautiously eliminated the threat.\n\nThey were surprised to find that both of the Abyss Mages' shields had already become quite badly battered, and gazing upon the radiant glow from the Vision on Mika's right wrist, they seemed to realize something...\n\nThat day, the Reconnaissance Company's dinner was especially sumptuous. Everyone raised their glass to celebrate, while Mika himself seemed to be in shock, unable to wrap his head around what was happening.",
    "zh": "### 角色详细\n\n每次来到骑士团总部，米卡都会尽快解决与同僚的对接工作并悄无声息地离开。他不想影响任何人的工作节奏。\n\n只要被人搭话，他就容易过度紧张。一旦以礼貌的方式结束闲聊，他会立刻慌慌张张地逃开。\n\n骑士们知道这位年轻人名叫米卡，是同僚霍夫曼的弟弟，施密特家的次子，目前隶属于游击小队。\n\n但他们并不了解米卡的工作，也不清楚团内正在推广的新版军用地图正是米卡的工作成果。\n\n新版地图汇集了蒙德周边大多数区域的地形数据，还附有大量的实用标示——\n\n包括所有道路的路况、潜在的魔物聚集区与可供据守的高地位置、自然资源的类型与开发状况…详尽得令人眼花缭乱。\n\n这些全都是米卡走遍蒙德各地，花费两年亲自勘测的成果。\n\n少数与米卡并肩作战过的骑士了解他的战斗风格，米卡习惯于并用长枪与手弩，这种战斗方式令他们印象深刻。\n\n不过他们都接受过米卡郑重的请求，尽可能不对他人提起米卡的事。\n\n「米卡很害怕引人注目，别说挨夸了，光是被人盯着看都会紧张得不行，我们这些被他帮过的前辈当然要照顾他的情绪！」\n\n### 角色故事1\n\n米卡来自一个和睦美满的家庭：母亲是蒙德的风土作家，父亲是退役的西风骑士，哥哥霍夫曼正为骑士团效力。\n\n小米卡刚识字的那段时间，父亲正陪着母亲在外地旅行，取材筹备新书。在此期间，照顾小米卡的责任就落到了哥哥霍夫曼肩上。\n\n然而，哥哥和骑士团的兄弟们打成一片，白天认真工作，晚上喝酒放纵，他自己的生活完全没有规律，更别说管好弟弟了。\n\n反倒是小米卡早早养成了好习惯，白天照顾自己，晚上照顾哥哥。大部分孩子无忧无虑地玩耍时，小米卡已经可以将个人生活打理得井井有条，还经常为霍夫曼打理衣食住行。\n\n父母每周都会委托专人将信件带回蒙德，向两个孩子报平安。母亲文笔优美，她描摹沿途风景的语言像童话一样动人。小米卡喜欢对着信件查看地图，确认父母的位置，然后拿笔画出他们的旅行路线。想象父母这一路上的奇妙经历是他最快乐的事。\n\n不知不觉中，小米卡喜欢上了翻阅地图，他把许多地方的地形记得滚瓜烂熟。\n\n可惜，霍夫曼捎来扫兴的消息：「爸妈留下的蒙德地图太老，最初绘制的时候就不够准确，你白记了。」\n\n这也没有办法——有能力在野外自由活动的人基本都成了冒险家，一心想着委托和摩拉。地图？凑合着用就好。\n\n而有能力测绘地图的人大多不擅长战斗，亲自去野外测绘对他们而言太危险，有限的收入也不允许他们雇佣保镖。\n\n也许等到骑士团预算充裕那天就会找专家来解决这个问题了。不过目前的蒙德和平稳定，不知道这件事哪天才会被提上日程。\n\n小米卡陷入了沉思：像爸爸妈妈一样走遍地图每个角落，记录脚下大地的各种细节…世界上应该没什么比这更有意思的事了。\n\n于是，小米卡有了明确的人生目标：\n\n「就由我来当绘制地图的专家吧。」\n\n### 角色故事2\n\n父母返回蒙德后，米卡向他们坦白了自己的人生理想，他们万分欣慰，承诺全力支持米卡。\n\n从那天起，米卡把大量时间花在图书馆里，潜心自学提瓦特地理知识，勤奋练习绘图技巧。\n\n丽莎对这个懂礼貌、有天分又肯吃苦的孩子印象不错，经常帮米卡寻找相关书籍，指点他避开了不少弯路。\n\n经过长期钻研，米卡的水平得到了丽莎的肯定——「以你现在的水平去参加教令院选拔，说不定真的能入学呢。」\n\n此后，米卡开始寻找外出勘探的机会。正巧图书馆的熟人艾拉·马斯克需要一位向导，带她去僻静的野外与丘丘人交流。\n\n这就成为了米卡的第一份工作。结果，他俩虽然顺利抵达了目的地，但因沟通出现问题，反而被丘丘人结结实实揍了一顿…\n\n米卡将这次的挫折归咎于自己武力不足：「如果我不懂得保护自己，就无法顺利勘查陌生区域。」\n\n事后，米卡再次拿出自己学习地理知识的劲头，跟着哥哥苦练战斗技巧。或许是因为体质还不错，米卡很快就学得有模有样了。\n\n正巧此时，骑士团在三年后远征的计划初步确定。他们还需要再招些人填补空缺，这其中就有「前进测绘员」的岗位。\n\n「前进测绘员」的要求相当严苛：应征者需有一定的地图测绘能力，因环境危险，应征者还将长期担任部队前锋，因此必须懂得如何与危险魔物战斗。\n\n米卡的机会来了，比预想的情况还美妙，美妙得令他生畏…\n\n他本以为自己会以外聘顾问的形式加入队伍发挥所长，没想到骑士团要的是编内成员，还是处于矛头位置的精锐。他曾有过犹疑和胆怯，生怕自己不配这种「强者才能胜任」的重担。\n\n好在这怯意很快就被父亲和哥哥的鼓励驱散了，他们的话米卡始终记得：\n\n「不用给自己太高的要求，只需要为团队献出全力，就算得上尽职尽责。」\n\n「大部分西风骑士都是我们这样的平凡之人。平凡的骑士们依靠出色的团队合作完成任务，不输那些独行的强者。」\n\n就这样，他抓住机会，报名参加了西风骑士团。\n\n想到将来的工作内容将是自己热爱之事，米卡就不那么恐慌了。\n\n### 角色故事3\n\n米卡报名参加选拔的消息很快传遍整个西风骑士团。\n\n「霍夫曼的弟弟也要加入骑士团了！那个会照顾醉鬼的小米卡要入团了！」\n\n天真的米卡从没想过自己会成为目光焦点。他紧张得呼吸加速，心跳紊乱，生怕一旦表现不好就会令父亲蒙羞，害哥哥遭受非议，进而导致施密特家名声受损。\n\n由于施密特家已有多人入团，为彰显选拔的公平性，骑士团决定提高考核难度，并对民众公开考核过程。\n\n考虑到远程途中的实际情况，考核官凯亚出了一系列近乎严苛的考题：\n\n穿戴全套盔甲，靠有限补给于限定时间内负重越野至龙脊雪山的半山腰；\n\n在没有任何参考信息的情况下，顶着魔物的袭扰重新绘制特定区域的地图…\n\n所幸米卡做足了功课，他拼尽全力闯过了最艰难的关卡，成为了三名通过考核的受试者之一。\n\n途中，其余两名受试者或多或少得到了米卡的帮助，对米卡来说，他们不是竞争对手而是将来的同僚。\n\n大团长法尔伽非常看好这个富有团队意识的新人。他决定将其他两人分别补充给骑兵小队与调查小队，米卡则随他一同前去远征。\n\n此外，法尔伽每周都会抽空教导米卡战斗技巧，并为米卡布置各种「作业」。\n\n后来，米卡被编入了游击小队。与那位性格特别的队长相处，对于米卡的团队沟通能力也是一种磨练，这可以帮他提早适应精英荟萃的远征队。\n\n就这样，加入骑士团后，米卡一边在游击小队执勤，作为前进测绘员在危险地域历练，一边接受法尔伽的提点，不断完善测绘地图之外的能力。\n\n老实又年轻的新人米卡逐渐成长，开始变得沉着可靠，只是他自己还没意识到这一点罢了。\n\n### 角色故事4\n\n得益于长期实战的锤炼，米卡不到两年就成为了游击小队的核心成员，完成的任务不可胜数。\n\n计划中的日期很快到来，远征队即将出发。\n\n送行宴上，大团长法尔伽明显因米卡右腕的「神之眼」而惊喜，但亲自与米卡比划几下后，他给出了「很棒，但还远远不够」的评价。\n\n彼时的米卡尚未理解大团长的话。直到远征队正式出发，深入危险禁区，米卡才逐渐明白大团长究竟将怎样的魔物作为了参考对象。\n\n那些难以名状的、游荡着的「东西」，对任何落单的骑士而言都堪称梦魇。\n\n前锋们探明前路的进度决定了远征队推进速度。出勤最频繁那段日子，米卡一天只能休息半个小时。\n\n前所未有的高压让米卡倍感吃力，何况在未知的危险外，还有着虎视眈眈的另一支势力…\n\n某个疲惫的深夜，准备休息的米卡突然收到了另一队前锋的警告：骑士团遭遇了敌情。\n\n米卡匆匆抵达现场时，法尔伽早已带着他的得力部下们摆开了战阵。\n\n夜幕深处，隐约可见高大士兵构成的人墙，他们无声伫立，似是没有生气的战争机器。\n\n而在对方阵线的中央，可见一道漆黑、锐利的身影。对方的面容似乎无法被火光照亮，唯有幽蓝的双目氤氲着摄人心魄的暗芒。\n\n在同僚的提醒下，米卡得知了对方的身份——愚人众执行官「队长」，以及直属他的尖兵。\n\n西风骑士团的前锋撞上了愚人众的前哨，发生了摩擦，双方的神经都太过敏感，不断申请增援，最终惊动了双方的最高长官。\n\n空气中的硝烟味太过浓烈，危机感迅速侵入米卡的脑海，让他四肢麻木，手脚冰凉。\n\n米卡不断想象，要是对峙演变成冲突，自己该怎么办…\n\n尤其是那位执行官，米卡只觉得，自己根本没可能招架住对方的随手一击。\n\n杂乱的念头和沉重的疲惫感让米卡呼吸加速，难以集中注意力。\n\n法尔伽却表现得游刃有余，遥遥向对方打了个招呼，提着武器独自走向「队长」。「队长」也示意部下待命，缓慢上前。\n\n在双方紧张到极点的情况下，法尔伽与「队长」进行了一番短暂的商谈。\n\n随后，漆黑的身影稍稍抬手，愚人众的尖兵们便跟在他身后一同离去，犹如鬼影消散，无声无息。\n\n在场的西风骑士们无不长舒一口气，甚至有人止不住战栗。可法尔伽回到骑士团的阵线后，还表现得轻松自在：\n\n「好一场偶遇！要不是现在的情况很特别，我还真想找个机会和他切磋两下！」\n\n「他不是个固执的家伙，他也明白，在陌生的土地上交战，对我们两边都没好处…」\n\n直到此时，米卡才深刻地意识到，自己刚刚踏在了战争的导火索上，好这根导火索并未被引燃。\n\n「队长」的强大压迫感、大团长处理危机时的稳重…这场对峙深深刻入了米卡的记忆。\n\n他反省良久：虽说自己的实力正在快速提升，但还是差了太多火候，根本没法从容应对这样的局面。\n\n不能只满足于为团队献出全力，必须再刻苦一点，变得更加可靠，妥善处理各种意外…\n\n### 角色故事5\n\n好在之后远征途中米卡再未遇到过分惊险的事，顺利度过了最为艰苦的时期。\n\n蒙德「归风佳酿节」期间，米卡带着大团长的信件重返蒙德，回归了游击小队。\n\n游击小队的同伴们欣喜之余也倍感惊奇：米卡的实力突飞猛进，原本三名前锋才能完成的任务如今只需他一人就能轻松搞定。\n\n考虑到大团长信中曾模糊地提到过愚人众，米卡则是直属大团长的骨干…随着同僚们议论不断，一条奇怪的逻辑链诞生了——\n\n「米卡和愚人众交过手！米卡大概和愚人众的精锐交过手！米卡有可能跟着大团长一起对付过愚人众的执行官！」\n\n「要不然，米卡怎么会突然变得这么强呢！现在他也是我们的大英雄了，不管什么事都可以拜托他！」\n\n实际上，米卡不过是在远征途中得到了充分的历练，其他西风骑士也有不同程度的进步，只不过他们还没归来，无法形成对比罢了。\n\n对于这些离谱的传言，米卡不知该怎么去解释，便请教了琴和凯亚。\n\n琴谨慎地告知各个小队的负责人，希望大家保持理智，不要传播缺少证据的消息，另外，远征中的许多事宜都属于军事机密，本就应谨慎对待。\n\n凯亚则不以为然，还在打趣——西风骑士们多多少少对愚人众有点怨言，「米卡痛揍愚人众」这样的传言，好像对士气有利呢。\n\n总之，既然代理团长已经知道这一情况，又没有给别人添麻烦…米卡也就不那么恐慌了。\n\n他一如既往地执勤，遇上请求帮助的同僚就尽全力伸出援手。\n\n只不过，传闻太夸张，太被别人信任，好像也会带来困扰…\n\n最近向米卡借阅新地图、请米卡帮忙维护武器、甚至是蹭一口游击小队行军餐的同僚都变多了。\n\n这些同僚好像都想得到「前进测绘员的气势」，让自己像米卡那样快快变强。\n\n### 「整合型前进测绘装置」\n\n米卡随身携带的精巧装置，形如一册厚重的书本。\n\n这件装置由米卡与调查小队的技术人员一同开发，关键部件采用了阿贝多最新的炼金术成果——\n\n装置内部安置了一本记事簿，可用于记录信息，每张纸页都能被快速拆卸替换，便于直接产出地图。\n\n外壳背部的板材中则蚀刻着致密的纹样，通过对纹样注入元素力即可激活背板外的棱形部件，向目标扇区释放探测用「波束」。\n\n接收「波束」碰撞目标物后反弹的回波，计算发射与接收的时间差，就能进行相对精准的测距；而不断加快释放「波束」的节奏，增大「波束」的宽度后，即可将一片狭小区域的地形立体地描摹。\n\n这一功能可以大大提高绘制地图时的准确度。可惜，一切探测所得的信息和计算过程都需要使用者用脑力来处理。\n\n只有原本就对于目标地形极为熟悉，能将平面地图准确记下，并具备极强空间认知力的精英，才能正常运用该功能。\n\n因此，能将这件装置顺利运用的前进测绘员，仅有米卡一人，使用的频率也不宜太高。\n\n原本计划列装其他小队的改进型设备最终都被储存起来，用来为米卡的装置提供零件。\n\n它是米卡作为最优秀的前进测绘员的得力助手与荣誉象征，但米卡从不向其他人提起它的精妙之处。\n\n那样的行为在米卡看来就像是一种炫耀，还有可能给阿贝多带去额外的工作，增添不少麻烦…避免为好。\n\n### 神之眼\n\n米卡曾经历一次生死攸关的危机。\n\n那是在刚刚加入游击小队后不久，米卡接到任务，照常独自行动，前往一片情报失效的区域，重新绘制那里的地形细节。\n\n他蹑手蹑脚地踏入废墟，却不慎碰落了断壁上的石块，惊扰了黑暗中的两位深渊法师。\n\n烈焰交织，元素的奔流瞬间吞没米卡，像是要将他彻底绞碎，蒸煮成魔物的佳肴。\n\n痛苦与慌乱侵入感官，唯有一个念头还留存在米卡的意识中——必须摆脱这些敌人，警告后方的同伴。\n\n「就算是游击小队的前辈…遭遇了这种伏击…也会陷入危险！」\n\n前进测绘员的职责，正是让同伴避开这样的险境。\n\n两位深渊法师拍手叫好，正要让其他潜藏的魔物解除伪装，旋转的长枪就已撕开火幕，漫天冰雾绽放，压制了废墟中的高温。\n\n等到深渊法师们回过神来，米卡已经远远逃开，还不忘高声道歉：\n\n「对不起！下次我会先敲门，让前辈们和你们堂堂正正对决的！」\n\n米卡口中的「下次」很快就到来了，游击小队的主力得到了情报，接踵而至，谨慎地清除了这些伏兵。\n\n同僚们讶异地发现，两名深渊法师的元素护罩早已残破不堪。看着米卡右腕光彩璀璨的「神之眼」，他们似乎明白了什么…\n\n那一天，游击小队的晚饭格外丰盛，大家都为米卡举杯庆祝，只有米卡本人还惊魂未定，云里雾里。"
  },
  "description": {
    "ru": "### О персонаже\n\nПоявившись в штабе Ордо Фавониус, Мика старается как можно скорее обсудить все рабочие вопросы и незаметно уйти, чтобы не мешать работе других рыцарей ордена. Мика всегда нервничает, если с ним заводят разговор на посторонние темы, и в панике убегает сразу после того, как вежливо свернёт беседу. Рыцари знают, что этого молодого человека зовут Мика, что он младший брат Хоффмана, второй сын семьи Шмидт, а сейчас - один из членов разведывательного отряда. Но они не имеют понятия, какой работой занят Мика, и даже не знают, что новой версией военной карты орден полностью обязан Мике. В новой карте содержатся подробные данные по рельефу местности в Мондштадте и его окрестностях, снабжённые удобными примечаниями: состояние дорог, возможное скопление монстров, возвышенности, подходящие для обороны, типы природных ресурсов и их распределение... Карта составлена настолько подробно, что при взгляде на неё разбегаются глаза. Это результат двухлетних изысканий Мики, когда он исходил весь Мондштадт вдоль и поперёк. Некоторые рыцари, сражавшиеся бок о бок с Микой, знают, что он прекрасно владеет копьём и арбалетом, его уникальный стиль ведения боя оставляет неизгладимое впечатление. Но после настойчивых просьб Мики они стараются поменьше распространяться о его умениях.\n\n«Мика боится лишнего внимания. Простой взгляд в глаза может заставить его нервничать, а если вы начнёте расточать комплименты, Мика под землю провалится от неловкости. Он много нам помогал - само собой, мы должны заботиться о его чувствах!»\n\n### История персонажа 1\n\nМика вырос в любящей семье. Его мать - писательница, отец - отставной рыцарь Ордо Фавониус, а старший брат Хоффман - действующий член рыцарского ордена. Когда Мика едва выучился читать, его мать отправилась путешествовать в поисках материала для новой книги, а отец её сопровождал. Присматривать за Микой пришлось Хоффману. Но днём Хоффман был занят службой, а по ночам пьянствовал со своими друзьями из ордена. Его собственная жизнь напоминала бардак, так что о Мике он позаботиться толком не мог. Зато маленький Мика научился заботиться и о себе, и о старшем брате, когда тот за полночь приходил пьяным домой. Пока сверстники Мики резвились и играли, он научился управляться с хозяйством, наладил режим, готовил Хоффману еду, приводил в порядок его одежду. Каждую неделю родители Мики отправляли с нарочным письмо в Мондштадт, чтобы дети за них не волновались. Мать Мики превосходно владела словом, её описания пейзажей читались увлекательно, словно сказки. Мика любил читать письма родителей, а потом отмечать их местоположение на карте и прочерчивать маршрут. Он мог часами представлять себе захватывающие приключения родителей в дороге. Постепенно Мика полюбил рассматривать карты, даже выучил наизусть топографию некоторых районов. Но Хоффману пришлось его разочаровать: «Карта Мондштадта, которую оставили родители, давно устарела. Она всегда была не особенно точной, так что вся твоя работа пропала даром». Впрочем, это было ожидаемо. В конце концов, смельчаки, способные исследовать дикие местности, обычно становились искателями приключений, для которых поручения и мора превыше всего. А карты - что карты? Обойдёмся теми, что есть. Опытные картографы зачастую не обладали боевыми навыками, позволяющими отправиться в дикую местность, и не могли себе позволить нанять телохранителей. Возможно, когда-нибудь у рыцарского ордена будет достаточно средств, чтобы пригласить хорошего картографа и обновить карту. Но пока в Мондштадте царили мир и благодать, этот план казался несбыточным. Маленький Мика погрузился в раздумья: «Если бы я мог отправиться в путешествие, как папа и мама... Обойти весь мир и составить подробную карту... лучшего желать нельзя». С тех пор у Мики появилась ясная цель в жизни: «Я стану специалистом по картографии».\n\n### История персонажа 2\n\nВернувшись в Мондштадт и узнав о цели, которую поставил перед собой Мика, родители очень обрадовались и пообещали, что во всём его поддержат. С того дня Мика стал проводить много времени в библиотеке, изучая книги по географии Тейвата и упражняясь в картографировании. Воспитанный, одарённый и трудолюбивый мальчик произвёл хорошее впечатление на Лизу, поэтому она много помогала Мике в поиске толковых книг, чтобы он не тратил время на устаревшие тома. Мика долго сидел над книгами, и в конце концов Лиза была вынуждена признать: «Твоих нынешних знаний хватит даже для поступления в Академию». Тогда Мика стал искать способы применить свои знания на практике. И как раз тогда Элла Маск, с которой он познакомился в библиотеке, искала проводника, чтобы отправиться в отдалённый район и пообщаться с хиличурлами. Так Мика получил своё первое задание. Им удалось добраться до места, но хиличурлы недопоняли, что они хотят сказать, разозлились и крепко их избили... Мика пришёл к выводу, что это произошло, потому что он совсем не умеет сражаться.\n\n«Пока я не умею за себя постоять, я никогда не смогу свободно исследовать неизведанные территории».\n\nПосле того случая Мика стал брать у Хоффмана уроки боевых искусств с тем же усердием, с каким раньше изучал картографию. К счастью, ему повезло с природными данными, и он быстро усвоил основы. По случайному совпадению, в ордене тогда как раз готовили план экспедиции, которая должна была состояться три года спустя. Оставалось ещё несколько вакансий, в том числе должность передового геодезиста. Требования к кандидату были очень строги: он должен был разбираться в картографии, а поскольку экспедиция планировалась в довольно опасном районе, ещё ему следовало уметь работать на передовой и обладать необходимыми боевыми навыками, чтобы сражаться с монстрами. Мика понимал, что это его шанс, о такой возможности он не мог даже мечтать... Вообще-то он думал, что однажды присоединится к ордену в качестве приглашённого консультанта. Теперь же оказалось, что ордену нужен свой картограф, полноправный член экспедиции, который будет работать на передовой. Сначала Мика сомневался в себе. Он боялся, что не достоин такой важной роли, ведь передовым геодезистом Ордо Фавониус может быть «только лучший из лучших». Поддержка отца и брата помогла ему одолеть сомнения, и он до сих пор помнит их слова: «Не требуй от себя слишком многого, самое главное - ты можешь быть полезен ордену, этого достаточно». «Большинство рыцарей - обычные люди, как ты и я. Но из обычных людей может собраться блестящий отряд, который ничем не уступит отряду сильнейших искателей приключений». Так что Мика рискнул и подал заявку на вакансию Ордо Фавониус. При мысли о том, что он сможет заниматься на работе любимым делом, страх отступал.\n\n### История персонажа 3\n\nНовость о том, что Мика откликнулся на вакансию передового геодезиста, быстро разошлась среди рыцарей Ордо Фавониус.\n\n«Младший брат Хоффмана тоже хочет стать рыцарем! Маленький Мика, который всегда заботился о своём пьяном брате, хочет к нам присоединиться!»\n\nЗастенчивый Мика никогда не думал, что окажется в центре внимания, он с трудом дышал, сердце бешено стучало. Мика боялся провалить отбор и опозорить отца, разрушить карьеру брата, испортить репутацию семьи. Поскольку многие члены семьи Шмидт состояли в рыцарском ордене, комиссия решила усложнить испытания для кандидатов и сделать процесс отбора публичным, чтобы избежать возможной предвзятости. С учётом требований, предъявляемых к геодезисту на передовой, Кэйа придумал целый ряд суровых испытаний, призванных строго оценить способности участников:\n\n- на время добраться по пресечённой местности до середины Драконьего хребта в доспехах, с тяжёлым грузом и ограниченным провиантом;\n\n- изучить местность, кишащую монстрами, и составить для неё новую карту без помощи справочных материалов;\n\nК счастью, Мика был хорошо готов, он старался как мог и прошёл отбор в тройке первых. Двум другим кандидатам, которые прошли отбор вместе с ним, Мика тоже помогал во время испытаний, потому что считал их не конкурентами, а будущими товарищами. Магистру Варке очень понравился новичок, который так здорово умеет работать в команде. Одного из прошедших отбор кандидатов перевели в отряд кавалерии, другого - в исследовательскую команду, а Мика отправился в экспедицию с магистром Варкой. С тех пор Варка каждую неделю учил Мику технике ведения боя и давал ему много «домашних заданий». Позднее Мика вступил в разведывательный отряд. Взаимодействие с капитаном отряда, которая отличается весьма странным характером, помогло Мике приобрести необходимые навыки общения и быстрее адаптироваться к работе в элитном разведывательном отряде. После вступления в рыцари Мика оттачивал технику картографирования, работая геодезистом на передовой и разведывая опасные места. Вместе с этим под руководством Варки он постоянно улучшал и другие свои навыки. Трудолюбивый новобранец постепенно окреп и сам не заметил, как превратился в серьёзного и надёжного рыцаря.\n\n### История персонажа 4\n\nМика неустанно совершенствовал свои навыки в реальном бою, благодаря чему менее чем за два года стал ключевым членом разведывательного отряда и выполнил бесчисленное количество заданий вместе со своими товарищами. Запланированная дата приближалась, и экспедиция вскоре должна была отправиться в путь. На прощальном вечере магистр ордена Варка был приятно удивлён, увидев новенький блестящий Глаз Бога на правой руке Мики. Однако после того, как он пригласил Мику на спарринг, магистр заключил, что его уровень способностей «поразительный, но недостаточно высокий». Мика не понимал, что это значит, пока экспедиция не вошла в опасную запретную зону, где он собственными глазами увидел монстров, которых магистр ордена Варка использовал в качестве эталона при оценке своих способностей. Это были неподдающиеся описанию, блуждающие существа, которые превращались в кошмар для любого незадачливого рыцаря, отставшего от отряда. Скорость движения авангарда определяла скорость движения всего отряда, поэтому в наиболее напряжённые дни Мика мог отдыхать не более получаса в день. Он впервые работал в таких условиях, и ему было непросто. Не говоря уже о том, что помимо неведомых опасностей, экспедиция находилась под пристальным вниманием другой стороны... Однажды, когда Мика готовился ко сну, он получил предупреждение от другого разведчика, что рыцари встретились с врагом. Когда Мика примчался на место, Варка уже сформировал боевой строй из своих верных подчинённых. В кромешной тьме ночи Мика смутно различал шеренгу солдат, безмолвно стоявших, словно безжизненные боевые механизмы. А прямо в центре вражеского строя возвышался тёмный силуэт. Факелы освещали местность, но Мика не мог разглядеть ничего, кроме жутких тёмно-синих глаз, которые, казалось, светились неведомым светом. Благодаря подсказке своего товарища по отряду, Мика узнал, что это был Предвестник Фатуи Капитано и его подчинённые. Оказалось, что рыцари Ордо Фавониус столкнулись с аванпостом Фатуи. Обе стороны не желали уступать и постоянно запрашивали подкрепления, в итоге дойдя до высшего командования. Мика чувствовал, как нарастает напряжение, как от предчувствия конфликта немеют конечности. Он мысленно представлял, как противостояние перерастает в вооружённый конфликт, и что нужно делать, если это произойдёт... Особенно это касалось Предвестника - Мика знал, что он будет абсолютно беспомощен... Путаница в голове и сильная усталость мешали сосредоточиться. Варка, в свою очередь, выглядел совершенно невозмутимым. Он издалека поприветствовал Предвестника и направился к нему с оружием в руках. Капитано тоже подал сигнал своим людям приготовиться, а сам начал медленно приближаться. Когда напряжение достигло пика, Варка и Капитано обменялись короткими фразами и, похоже, пришли к соглашению. Тёмный силуэт поднял руку, призрачные тени солдат Фатуи молча повернулись и безмолвно ушли вместе с ним. Все рыцари вздохнули с облегчением, но некоторые продолжали дрожать от страха. Когда Варка вернулся, он выглядел спокойным, как всегда:\n\n«Какая удивительная встреча! Если бы не особые обстоятельства, я бы с удовольствием вызвал его на дуэль!»\n\n«Он вовсе не глупец и прекрасно понимает, что вооружённое столкновение на чужой территории не сулит ничего хорошего обеим сторонам».\n\nТолько тогда Мика понял, что находился на грани боевого столкновения, но магистр ордена предотвратил конфликт. Как властное присутствие Капитано, так и невозмутимое спокойствие, с которым магистр ордена урегулировал кризис, произвели глубокое впечатление на Мику. Он долго размышлял об этом и пришёл к выводу, что, несмотря на то, что его сила росла, ему ещё предстоит пройти долгий путь, чтобы научиться правильно действовать в подобных ситуациях. Недостаточно просто делать всё возможное, чтобы помочь отряду. Он должен трудиться ещё усерднее и стать достаточно опытным, чтобы справляться с самыми разными обстоятельствами...\n\n### История персонажа 5\n\nК счастью, Мике не довелось столкнуться с чем-то слишком опасным, и он без особых трудностей преодолел сложный период. Во время Праздника вина он вернулся в Мондштадт с письмом от магистра ордена Варки и занял свою прежнюю должность в разведывательном отряде. Члены отряда были рады его возвращению и одновременно удивлены поразительным прогрессом, которого он добился, ведь он мог теперь легко выполнять задания, для которых обычно требовалось три разведчика. А если учесть, что в письме магистра ордена вскользь упоминались Фатуи, и что Мика был ключевым участником экспедиции под непосредственным командованием Варки... Его товарищи по отряду быстро связали эти два момента, и возникла странная логическая цепочка:\n\n«Мика противостоял Фатуи! Мика способен сражаться с элитными бойцами Фатуи! Мика сражался вместе с магистром ордена и одержал победу над Предвестником Фатуи!»\n\n«Иначе как он мог вдруг стать таким сильным? Мика - наш герой! Его можно просить о чём угодно - он всё для нас сделает!»\n\nПравда заключалась в том, что опыт Мики в экспедиции сыграл роль тренировки. Другие рыцари тоже в той или иной степени добились успехов, только они ещё не вернулись, поэтому Мику не с кем было сравнивать. Мика не знал, как относиться ко всем этим несуразным слухам, поэтому он обратился за советом к Джинн и Кэйе. Джинн уведомила командиров каждого отряда о необходимости придерживаться рационального подхода и воздерживаться от распространения домыслов, основанных исключительно на слухах. Кроме того, произошедшие во время экспедиции события считаются строго конфиденциальными, и к ним следует относиться с осторожностью. Кэйа, напротив, с удовольствием подшучивал на эту тему. Рыцари Ордо Фавониус в той или иной степени испытывали неприязнь к Фатуи, и слух о том, что «Мика хорошенько им наподдал», вполне мог поднять боевой дух. По крайней мере, Мика чувствовал себя спокойнее, зная, что действующий магистр в курсе произошедшего и знает, что он не собирался создавать неприятности. Он, как обычно, ходил на службу и делал всё возможное, чтобы помочь другим. Однако слухи на этом не прекратились, и Мика не раз попадал в неловкие ситуации. Всё больше и больше рыцарей подходили к нему, чтобы попросить новые карты, помочь с обслуживанием оружия или поделиться пайком. Казалось, все разделяли бездумную веру в то, что, проводя больше времени с Микой, они смогут стать такими же сильными, как он.\n\n### Передовое картографическое устройство\n\nЗамысловатое устройство в форме книги, которое Мика повсюду носит с собой. Оно было разработано Микой и техническими специалистами из исследовательской команды, а его ключевые компоненты изготовлены с использованием последних алхимических разработок Альбедо. В устройство встроен блокнот, созданный для быстрого создания и использования карт. Каждый из его листов можно легко вынимать и заменять. Сзади на устройстве вырезан сложный узор. Направление элементальной силы на узор активирует ромбовидный компонент на передней стороне устройства, который, в свою очередь, испускает волновой луч в форме веера в направлении цели. Расстояние между устройством и целью можно точно рассчитать, используя время, необходимое для отражения луча. Увеличивая частоту и амплитуду волнового луча, устройство создаст карту небольшого участка местности. Все эти функции значительно повышают точность карты, но, к сожалению, всё остальное, включая статистическую информацию и расчёты для конкретной местности, пользователь должен вычислить самостоятельно в уме. Только те, кто обладает отличными навыками пространственного мышления и обширными знаниями местности, способны в полной мере использовать эту функцию. Таким образом, Мика является единственным геодезистом, который может без труда работать с устройством, хотя использует его довольно редко. Были и другие импровизированные устройства, которые планировалось раздать другим командам, но в настоящее время они служат для снабжения запасными частями устройства Мики. Прибор был создан как верный помощник Мики и символ признания его лучшим геодезистом, но Мика никогда не рассказывал о его впечатляющих возможностях другим. Для Мики это выглядит как хвастовство, не говоря уже о том, что это может добавить работы Альбедо... А беспокоить других было последним, чего Мика хочет.\n\n### Глаз Бога\n\nОднажды Мика оказался на грани жизни и смерти. Это случилось вскоре после того, как он присоединился к разведывательному отряду. Информация об одном участке устарела, и Мика взял на себя труд уточнить детали местности. Он осторожно пробирался по руинам, когда нечаянно задел кусок камня от разрушенной стены, чем привлёк внимание двух магов Бездны, притаившихся в темноте. Когда языки пламени переплелись, его мгновенно охватил прилив элементальной силы, словно она собиралась искрошить его на куски и превратить в обед для монстров. Боль и паника заполнили его, а в сознании осталась только одна мысль - нужно бежать и предупредить других.\n\n«Эти монстры... Они представляют угрозу даже для самых опытных членов экспедиции...»\n\nВ обязанности фронтового геодезиста входило уберечь своих соратников от опасных ситуаций, подобных этой. Маги Бездны закричали от радости и уже собирались приказать другим монстрам выйти из укрытия, когда завесу пламени разорвало вращающееся копье. По руинам поплыл ледяной туман, мгновенно разогнав невыносимую жару. Когда маги Бездны, наконец, разобрались в ситуации, Мика уже скрылся вдали, продолжая извиняться достаточно громко, чтобы монстры услышали: «Простите! В следующий раз я обязательно постучу, прежде чем войти. Тогда мои старшие товарищи смогут сразиться с вами в честном бою!» «Следующий раз» наступил очень быстро - основные силы разведывательного отряда получили сообщение о монстрах и быстро, но осторожно устранили угрозу. Они с удивлением обнаружили, что щиты обоих магов Бездны были сильно повреждены, а, взглянув на сияние, исходящее от Глаза Бога на правой руке Мики, они всё поняли... В тот день ужин в разведывательном отряде был особенно роскошным. Все поднимали бокалы в честь торжества, а сам Мика, казалось, пребывал в шоковом состоянии и был не в состоянии осознать происходящее.",
    "en": "### Character Details\n\nWhenever he shows up at the Knights of Favonius headquarters, Mika always swiftly finishes any discussions to be had with his fellow knights, then quietly slips away to avoid becoming a hindrance to others' work.\nMika always gets nervous when someone strikes up a conversation with him, frantically scampering away right after politely putting an end to the idle chatter.\n\nThe knights know that the young man's name is Mika, and that he is Huffman's younger brother and the second son of the Schmidt family. They also know that he is a member of the Reconnaissance Company, but nothing much beyond that.\n\nFew are aware of what Mika's job entails, nor do they know that the widely-promoted, updated version of their military map is the fruit of his labors.\n\nThe new map consists of detailed statistical data regarding almost every corner of Mondstadt with practical markers indicating road conditions, areas with heightened monster activity, high ground that can serve as temporary strongholds, and the distribution of natural resources... The amount of detail could almost make your head spin.\n\nAll of this is the result of Mika's own labor throughout the two years he has spent traveling all across Mondstadt and investigating every inch of terrain he set foot on.\n\nKnights who have fought alongside Mika know that he finds using both lance and crossbow at the same time the most convenient, and his unique fighting style has left a lasting impression.\n\nHowever, they have also been solemnly \"warned\" by Mika to never speak of him to others unless absolutely necessary.\n\n\"Mika's terrified of drawing the attention of others — he'll get nervous if you so much as stare at him, to say nothing of showering him with compliments. He's been a great asset to the Knights and helped us out a lot, so respecting his boundaries is the least we can do as seniors!\"\n\n### Character Story 1\n\nMika comes from a loving family. His mother works as an author writing about local conditions, his father is a retired Knight of Favonius, and his older brother Huffman is a current member in the Knights' ranks.\n\nWhen Mika began learning to read, his mother went inspiration-gathering abroad with his father accompanying her. During that time, the responsibility of looking after little Mika landed in Huffman's hands.\n\nHowever, Huffman had already made the Knights of Favonius his second home — he was preoccupied with work during the day and indulged in drinking with his friends night after night. With his own life lacking organization, how was he expected to take care of his little brother?\n\nSo it was little Mika who learned to take care of both himself and his brother whenever he'd return home drunk at night. When other children his age were enjoying their childhood without a care, Mika had already learned to stick to an organized schedule, sometimes even helping Huffman with his everyday chores.\n\nWhile they were away, Mika's parents always made sure to send a letter back to Mondstadt every week to keep their children from worrying. Mika's mother, being an excellent writer, could somehow describe the scenery she's seen in a mesmerizing way akin to fairytales. Mika loved to read his parents' letters before looking for their exact location and marking out their travel route on a map. Picturing his parents' wonderful adventures was Mika's favorite pastime.\n\nBefore long, Mika developed a passion for reading maps, and even committed the terrain of many locations to memory.\n\nUnfortunately, Huffman had to ruin the mood when he broke the bad news to Mika: \"I'm afraid your efforts have been wasted on the map Mom and Dad left us. It's very outdated, and it wasn't very accurately drawn in the first place.\" But that was to be expected. After all, those who with the ability freely explore the wilderness would likely have all become adventurers with nothing but commissions and Mora on their minds. To them, just about any map would do.\n\nOn the other hand, most of those who knew how to draw decent maps were not skilled in combat, so it would be much too dangerous for them to survey the wilderness themselves. Not to mention their limited income, which wouldn't allow them to afford bodyguards. Perhaps the time would come when the Knights of Favonius finally had sufficient budget to hire experts to deal with matters like these, but with Mondstadt as peaceful as one could hope for, no one knew for sure when something as trivial as cartography could be put on the schedule. So little Mika thought to himself: If he could reach every corner of the world just like his parents, and record every detail of the terrain beneath his feet... That would be the most fun ever.\n\nFrom then on, Mika set a clear goal for himself.\n\n\"I'll become Mondstadt's expert cartographer.\"\n\n### Character Story 2\n\nWhen Mika's parents returned to Mondstadt, they were delighted to hear of Mika's new-found goal and promised to do whatever they could to support him.\n\nFrom that day on, Mika dedicated most of his time to poring over geography books and assiduously honing his drawing skills in the library.\n\nLisa took a liking to this polite, gifted yet hardworking child and often recommended books to him, guiding him towards the most efficient path.\n\nAfter some time, Mika gained Lisa's recognition — \"With your current skills and abilities, you just might qualify for studying at the Akademiya.\"\n\nIt was then that Mika began looking for opportunities to put his knowledge to the test. As it happens, Ella Musk, whom he had gotten acquainted with while studying at the library, happened to be looking for a guide for a language exchange trip to the secluded wilderness.\n\nAnd that became Mika's first real expedition. Though they did safely arrive at their destination, due to an error in Ella Musk's word choice, the pair ended up getting beaten by the hilichurls.\n\nMika concluded that this setback was due to his lack of combat prowess. \"I need to learn how to protect myself,\" he thought, \"or I won't be able to guarantee the success of my expeditions to unfamiliar areas.\"\n\nThereafter, Mika rode the momentum from his time spent learning in the library and began to learn fighting techniques from his brother. Luckily, Mika had a strong constitution and quickly grasped the basics.\n\nIt happened that the Knights of Favonius had just drafted their plan for an expedition set to depart three years later. They were still looking to recruit a few more members to fill some positions, and \"Front-Line Surveyor\" was among the open spots.\n\nThis role had strict prerequisites: those applying for the position should have some level of expertise in cartography, and due to potentially dangerous conditions, they would be leading the team from the front lines, making combat skills a must.\n\nThis was Mika's chance, but it all felt too much like a dream...\n\nMika initially believed that he would be invited into the team as an external consultant, but the position of Front-Line Surveyor would no doubt make him a full-fledged member of the expedition — and one crucial to the entire team. He was daunted by the thought at first, afraid that he wasn't worthy of such an important role that according to him, \"only the strongest would qualify for.\"\n\nHis doubts were soon dispelled by his father and brother's encouragement, and he remembers their words to this day:\n\n\"You don't have to ask too much of yourself. Doing your best to help will be more than enough.\"\n\n\"Most of the knights are just ordinary people like us, but once we put our strengths together as a team, even the strongest of adventurers would struggle to prove our equal.\"\n\nThus, Mika seized the opportunity and signed up for the position.\n\nHe felt reassured that he would, at least, be dedicating his time to what he loved.\n\n### Character Story 3\n\nWord of Mika signing up for the expedition spread like wildfire throughout the Knights of Favonius.\n\n\"Huffman's little brother will be joining us! The little kid who always takes care of that drunkard will be joining the Knights!\"\n\nThe anxiety from unexpectedly becoming the center of attention made his breaths quicken as his heart pounded — Mika was afraid of failing the Knights' assessment and disgracing his father, ruining his brother's career, or worse, ruining the reputation of his family name.\n\nConsidering that many members of the Schmidt family had already joined their ranks, the Knights of Favonius decided to raise the bar for entry and make the whole assessment process public in order to make the selection as fair as possible.\n\nTaking real-life scenarios into consideration, lead examiner Kaeya came up with a series of challenges that strictly assessed the participants' abilities:\n\nHiking up Dragonspine while wearing full armor and carrying a heavy load;\n\nMapping out a monster-infested region without the aid of any reference material...\n\nLuckily, Mika came well-prepared and gave it his all, eventually passing the most difficult challenge and becoming one of three successful candidates.\n\nThe other two candidates had both received Mika's aid along the way as well — to him, they were more like future teammates than competitors, in any case.\n\nMika's excellent exhibition of teamwork gained the recognition of Grand Master Varka, who allocated the two other new recruits to the Cavalry Company and Investigation Team, while personally taking Mika in to go with him on his expedition.\n\nEvery week, Varka would teach Mika combat techniques and give him assorted \"homework\" to complete.\n\nMika would later join the Reconnaissance Company. Communicating with its rather unusual Captain further strengthened his communication skills, which would help him greatly when working with the elite knights of the expedition team.\n\nAfter joining the Knights, Mika honed his cartography skills while investigating dangerous locations as a Front-Line Surveyor while receiving pointers on how he might improve his other skills from Varka.\n\nThe diligent young recruit quickly became a calm and reliable knight — though it seems as though he has yet to realize that himself.\n\n### Character Story 4\n\nAs Mika continuously refined his skills in real-life combat, he became a core member of the Reconnaissance Company in less than two years, completing countless missions alongside his teammates.\n\nThe scheduled date drew near, and the expedition team was soon about to depart.\n\nAt the send-off party, Grand Master Varka was pleasantly surprised by the shiny new Vision on Mika's right wrist. But after personally inviting Mika to spar, he concluded that Mika's current abilities were \"remarkable, but far from enough.\"\n\nMika didn't figure out what that meant until the expedition team entered a dangerous restricted area, where he finally saw with his own eyes the monsters Grand Master Varka had used as a reference when judging his powers.\n\nThose unnamable, wandering creatures could become a nightmare for any knight unfortunate enough to stray away from the team.\n\nThe speed of their scouts in the vanguard determined how fast the whole expedition team proceeded, so during the days when the team was the busiest, Mika could only rest for half an hour a day.\n\nIt was Mika's first time working under such high pressure, and he did so with great difficulty. Not to mention that apart from dangers of the unknown, the expedition team was under the watchful gaze of another party...\n\nOne day, when Mika was getting ready to call it a night, he received a warning from another scout that the Knights had encountered enemies.\n\nWhen Mika hurried on scene, Varka had already drawn up battle lines with his trusty subordinates.\n\nIn the depths of the pitch-dark night, Mika could vaguely make out a line of soldiers, silently standing there as if they were lifeless war machines.\n\nAnd right in the middle of the enemy formation was a dark, distinct silhouette. Even though torches lit the area, Mika could see nothing but their eerily dark blue eyes that seemed to glow with an uncanny aura.\n\nAt his teammate's reminder, Mika learned of their identity — the Fatui Harbinger known as \"The Captain\" and his direct, elite subordinates.\n\nAs it turned out, their vanguard had bumped into Fatui scouts and an altercation had ensued, resulting in both sides getting jumpy and continuously requesting reinforcements, eventually alerting their respective commanders.\n\nThe scent of gunpowder was thick in the air, the sense of crisis turned Mika's limbs numb and cold.\n\nHe couldn't help visualizing the confrontation escalating into an armed conflict, and what he should do if such a thing were to happen...\n\nThe Harbinger, in particular — Mika knew that he would be utterly helpless to parry a single half-hearted swipe from this person.\n\nHis jumbled thoughts and exhaustion made it difficult to breathe or focus.\n\nVarka, however, seemed completely unfazed. He greeted the Harbinger from afar and walked towards him with his weapon in hand. The Captain, too, signaled his men to stand by as he began slowly stepping forward.\n\nAs the tension between the two parties reached its peak, Varka and The Captain briefly conversed and seemed to reach an agreement.\n\nThe dark silhouette raised his arm, and the ghostly shadows of the Fatui soldiers silently turned and departed with him.\n\nThe Knights all heaved a sigh of relief, and some were even trembling with fear. But when Varka returned to the Knights' formation, he looked as relaxed as ever.\n\n\"Well, that was a surprise! If it weren't for our unique circumstances, I would've loved to invite him for a duel!\"\n\n\"And it's not like he's a stubborn fellow. He's well aware that engaging in battle in a strange and foreign land would've been disadvantageous for both of us.\"\n\nIt was until then that Mika realized they had been on the precipice of war, and conflict had been avoided only because the Grand Master had been there to prevent it.\n\nThe Captain's overpowering presence and the calmness with which Grand Master Varka handled the crisis both left a profound impression in Mika's mind.\n\nMika reflected on this experience for a long time and concluded that although he had been improving in strength, he still had a long way to go when it came to dealing with situations like that.\n\nThere was more to be done than just doing his best to help the team. He had to work harder to become a reliable Knight who could handle all manner of incidents...\n\n### Character Story 5\n\nFortunately, Mika would not run into anything exceedingly dangerous during the expedition and smoothly made it past that most difficult period.\n\nDuring Mondstadt's Weinlesefest, Mika returned to Mondstadt with Grand Master Varka's letter and resumed his post in the Reconnaissance Company.\n\nThe members of the Reconnaissance Company were both excited at his return and surprised at the astonishing progress he had made — for he could now easily complete tasks that usually required three forward scouts.\n\nAnd considering that the Grand Master's letter had vaguely mentioned the Fatui, and that Mika had been a key member on the expedition under Varka's direct command... His teammates quickly connected the dots and a strange chain of logic emerged:\n\n\"Mika fought against the Fatui! Mika might've fought against Fatui elites! Mika must've fought alongside the Grand Master and won a battle against a Fatui Harbinger!\"\n\n\"How else could he have become this strong all of a sudden? Mika's our hero! He can now do anything for us!\"\n\nTruth be told, Mika had simply accrued a great deal of experience — the other Knights who had gone had also made progress to varying extents. They simply had yet to return, and thus no valid comparison could be made.\n\nMika didn't know how to deal with all the absurd rumors, and so he consulted Jean and Kaeya for advice.\n\nJean informed the leader of each company to remain rational and refrain from spreading rumors based purely on speculation. Besides, many matters regarding the expedition were considered highly confidential and should be treated with discretion.\n\nKaeya, on the other hand, seemed to enjoy joking about the rumors. Members of the Knights of Favonius all more or less held some sort of dislike for the Fatui, and a rumor that says \"Mika gave the Fatui a good beating\" could very well boost morale.\n\nWhatever the case, Mika felt greatly reassured now that the Acting Grand Master had been made aware of the situation and was comforted to know that he hadn't caused any trouble for anyone.\n\nHe reported to duty as usual and made sure he did all he could to help others.\n\nBut the exaggerated rumors couldn't be un-spread, and Mika has found that gaining too much trust comes with its own fair share of difficulties...\n\nRecently, more Knights have been coming up to him to borrow a new map, ask for help maintaining a weapon, or request a share of the Reconnaissance Company's field rations.\n\nAll of them seem to hope that some of his powers might rub off on them so that they can become stronger quickly, just like him.\n\n### Multipurpose Front-Line Surveying Device\n\nAn intricate book-shaped device Mika carries with him wherever he goes.\n\nIt was developed by Mika and technicians from the Investigation Team, and its key components were made using Albedo's latest alchemical creations.\n\nA notebook is embedded in the device's interior that can be used to record information. Designed to facilitate the quick production and use of maps, each of its pages can be conveniently removed and replaced.\n\nAn elaborate pattern is carved on to the back panel of the device. Channeling elemental power into the carving will activate the prism-shaped component outside said panel, which will in turn fire a \"wavebeam\" towards a fan-shaped target region.\n\nThe distance between the device and the target region can then be accurately calculated using the time taken for the beam to bounce back. By increasing both the frequency and amplitude of the beam, the device will generate a sketch of a small area of terrain.\n\nThis function can greatly improve the accuracy of a map, but regrettably, everything else — including the statistical information and calculations regarding the terrain in question — has to be computed in the user's mind.\n\nOnly those with excellent spatial reasoning skills and an extensive knowledge of the target terrain are capable of making full use of this function.\n\nThus, Mika became the only Front-Line Surveyor who could use the device without difficulty, and its overall usage rate is not very high.\n\nThere had been other improved devices originally planned for distribution to other teams, but they have been put into storage, to be used as spare parts for Mika's device.\n\nThe device is Mika's trustiest helper in his work and a symbol of honor for being the best surveyor, but Mika has never once mentioned its impressive features to others.\n\nTo Mika, that feels too much like bragging, not to mention that it could potentially give Albedo extra work... Troubling others is the last thing Mika ever wants, after all.\n\n### Vision\n\nMika was once in a life-or-death situation.\n\nThis was not long after he joined the Reconnaissance Company — the information on a certain area was no longer valid, and Mika had taken up the task to update the details of its terrain on his own.\n\nHe slowly crept into the ruins, only to accidentally knock off a piece of stone from the broken wall, alerting two Abyss Mages lurking in the dark.\n\nAs the flames intertwined, a rush of elemental power instantly engulfed him as if it was about to crush him into pieces and turn him into the monsters' next meal.\n\nPain and panic flooded his senses, and only one thought remained in his consciousness — he needed to escape and warn others.\n\n\"These monsters... They'd be a threat to even the most experienced members in the company...!\"\n\nIt was the responsibility of a front-line land surveyor to keep their teammates from dangerous situations like this.\n\nThe Abyss Mages shrieked in glee and were about to command other monsters to come out of hiding when a spinning spear tore the curtain of flames apart. An icy mist burst across the ruins, clearing the unbearable heat in an instant.\n\nWhen the Abyss Mages finally made sense of the situation, Mika had already fled far away, though still apologizing loudly enough for the monsters to hear:\n\n\"I'm sorry! I'll remember to knock before entering next time. That way, my seniors can fight you fair and square!\"\n\n\"Next time\" soon came — the Reconnaissance Company's main force were notified of the monsters and swiftly but cautiously eliminated the threat.\n\nThey were surprised to find that both of the Abyss Mages' shields had already become quite badly battered, and gazing upon the radiant glow from the Vision on Mika's right wrist, they seemed to realize something...\n\nThat day, the Reconnaissance Company's dinner was especially sumptuous. Everyone raised their glass to celebrate, while Mika himself seemed to be in shock, unable to wrap his head around what was happening.",
    "zh": "### 角色详细\n\n每次来到骑士团总部，米卡都会尽快解决与同僚的对接工作并悄无声息地离开。他不想影响任何人的工作节奏。\n\n只要被人搭话，他就容易过度紧张。一旦以礼貌的方式结束闲聊，他会立刻慌慌张张地逃开。\n\n骑士们知道这位年轻人名叫米卡，是同僚霍夫曼的弟弟，施密特家的次子，目前隶属于游击小队。\n\n但他们并不了解米卡的工作，也不清楚团内正在推广的新版军用地图正是米卡的工作成果。\n\n新版地图汇集了蒙德周边大多数区域的地形数据，还附有大量的实用标示——\n\n包括所有道路的路况、潜在的魔物聚集区与可供据守的高地位置、自然资源的类型与开发状况…详尽得令人眼花缭乱。\n\n这些全都是米卡走遍蒙德各地，花费两年亲自勘测的成果。\n\n少数与米卡并肩作战过的骑士了解他的战斗风格，米卡习惯于并用长枪与手弩，这种战斗方式令他们印象深刻。\n\n不过他们都接受过米卡郑重的请求，尽可能不对他人提起米卡的事。\n\n「米卡很害怕引人注目，别说挨夸了，光是被人盯着看都会紧张得不行，我们这些被他帮过的前辈当然要照顾他的情绪！」\n\n### 角色故事1\n\n米卡来自一个和睦美满的家庭：母亲是蒙德的风土作家，父亲是退役的西风骑士，哥哥霍夫曼正为骑士团效力。\n\n小米卡刚识字的那段时间，父亲正陪着母亲在外地旅行，取材筹备新书。在此期间，照顾小米卡的责任就落到了哥哥霍夫曼肩上。\n\n然而，哥哥和骑士团的兄弟们打成一片，白天认真工作，晚上喝酒放纵，他自己的生活完全没有规律，更别说管好弟弟了。\n\n反倒是小米卡早早养成了好习惯，白天照顾自己，晚上照顾哥哥。大部分孩子无忧无虑地玩耍时，小米卡已经可以将个人生活打理得井井有条，还经常为霍夫曼打理衣食住行。\n\n父母每周都会委托专人将信件带回蒙德，向两个孩子报平安。母亲文笔优美，她描摹沿途风景的语言像童话一样动人。小米卡喜欢对着信件查看地图，确认父母的位置，然后拿笔画出他们的旅行路线。想象父母这一路上的奇妙经历是他最快乐的事。\n\n不知不觉中，小米卡喜欢上了翻阅地图，他把许多地方的地形记得滚瓜烂熟。\n\n可惜，霍夫曼捎来扫兴的消息：「爸妈留下的蒙德地图太老，最初绘制的时候就不够准确，你白记了。」\n\n这也没有办法——有能力在野外自由活动的人基本都成了冒险家，一心想着委托和摩拉。地图？凑合着用就好。\n\n而有能力测绘地图的人大多不擅长战斗，亲自去野外测绘对他们而言太危险，有限的收入也不允许他们雇佣保镖。\n\n也许等到骑士团预算充裕那天就会找专家来解决这个问题了。不过目前的蒙德和平稳定，不知道这件事哪天才会被提上日程。\n\n小米卡陷入了沉思：像爸爸妈妈一样走遍地图每个角落，记录脚下大地的各种细节…世界上应该没什么比这更有意思的事了。\n\n于是，小米卡有了明确的人生目标：\n\n「就由我来当绘制地图的专家吧。」\n\n### 角色故事2\n\n父母返回蒙德后，米卡向他们坦白了自己的人生理想，他们万分欣慰，承诺全力支持米卡。\n\n从那天起，米卡把大量时间花在图书馆里，潜心自学提瓦特地理知识，勤奋练习绘图技巧。\n\n丽莎对这个懂礼貌、有天分又肯吃苦的孩子印象不错，经常帮米卡寻找相关书籍，指点他避开了不少弯路。\n\n经过长期钻研，米卡的水平得到了丽莎的肯定——「以你现在的水平去参加教令院选拔，说不定真的能入学呢。」\n\n此后，米卡开始寻找外出勘探的机会。正巧图书馆的熟人艾拉·马斯克需要一位向导，带她去僻静的野外与丘丘人交流。\n\n这就成为了米卡的第一份工作。结果，他俩虽然顺利抵达了目的地，但因沟通出现问题，反而被丘丘人结结实实揍了一顿…\n\n米卡将这次的挫折归咎于自己武力不足：「如果我不懂得保护自己，就无法顺利勘查陌生区域。」\n\n事后，米卡再次拿出自己学习地理知识的劲头，跟着哥哥苦练战斗技巧。或许是因为体质还不错，米卡很快就学得有模有样了。\n\n正巧此时，骑士团在三年后远征的计划初步确定。他们还需要再招些人填补空缺，这其中就有「前进测绘员」的岗位。\n\n「前进测绘员」的要求相当严苛：应征者需有一定的地图测绘能力，因环境危险，应征者还将长期担任部队前锋，因此必须懂得如何与危险魔物战斗。\n\n米卡的机会来了，比预想的情况还美妙，美妙得令他生畏…\n\n他本以为自己会以外聘顾问的形式加入队伍发挥所长，没想到骑士团要的是编内成员，还是处于矛头位置的精锐。他曾有过犹疑和胆怯，生怕自己不配这种「强者才能胜任」的重担。\n\n好在这怯意很快就被父亲和哥哥的鼓励驱散了，他们的话米卡始终记得：\n\n「不用给自己太高的要求，只需要为团队献出全力，就算得上尽职尽责。」\n\n「大部分西风骑士都是我们这样的平凡之人。平凡的骑士们依靠出色的团队合作完成任务，不输那些独行的强者。」\n\n就这样，他抓住机会，报名参加了西风骑士团。\n\n想到将来的工作内容将是自己热爱之事，米卡就不那么恐慌了。\n\n### 角色故事3\n\n米卡报名参加选拔的消息很快传遍整个西风骑士团。\n\n「霍夫曼的弟弟也要加入骑士团了！那个会照顾醉鬼的小米卡要入团了！」\n\n天真的米卡从没想过自己会成为目光焦点。他紧张得呼吸加速，心跳紊乱，生怕一旦表现不好就会令父亲蒙羞，害哥哥遭受非议，进而导致施密特家名声受损。\n\n由于施密特家已有多人入团，为彰显选拔的公平性，骑士团决定提高考核难度，并对民众公开考核过程。\n\n考虑到远程途中的实际情况，考核官凯亚出了一系列近乎严苛的考题：\n\n穿戴全套盔甲，靠有限补给于限定时间内负重越野至龙脊雪山的半山腰；\n\n在没有任何参考信息的情况下，顶着魔物的袭扰重新绘制特定区域的地图…\n\n所幸米卡做足了功课，他拼尽全力闯过了最艰难的关卡，成为了三名通过考核的受试者之一。\n\n途中，其余两名受试者或多或少得到了米卡的帮助，对米卡来说，他们不是竞争对手而是将来的同僚。\n\n大团长法尔伽非常看好这个富有团队意识的新人。他决定将其他两人分别补充给骑兵小队与调查小队，米卡则随他一同前去远征。\n\n此外，法尔伽每周都会抽空教导米卡战斗技巧，并为米卡布置各种「作业」。\n\n后来，米卡被编入了游击小队。与那位性格特别的队长相处，对于米卡的团队沟通能力也是一种磨练，这可以帮他提早适应精英荟萃的远征队。\n\n就这样，加入骑士团后，米卡一边在游击小队执勤，作为前进测绘员在危险地域历练，一边接受法尔伽的提点，不断完善测绘地图之外的能力。\n\n老实又年轻的新人米卡逐渐成长，开始变得沉着可靠，只是他自己还没意识到这一点罢了。\n\n### 角色故事4\n\n得益于长期实战的锤炼，米卡不到两年就成为了游击小队的核心成员，完成的任务不可胜数。\n\n计划中的日期很快到来，远征队即将出发。\n\n送行宴上，大团长法尔伽明显因米卡右腕的「神之眼」而惊喜，但亲自与米卡比划几下后，他给出了「很棒，但还远远不够」的评价。\n\n彼时的米卡尚未理解大团长的话。直到远征队正式出发，深入危险禁区，米卡才逐渐明白大团长究竟将怎样的魔物作为了参考对象。\n\n那些难以名状的、游荡着的「东西」，对任何落单的骑士而言都堪称梦魇。\n\n前锋们探明前路的进度决定了远征队推进速度。出勤最频繁那段日子，米卡一天只能休息半个小时。\n\n前所未有的高压让米卡倍感吃力，何况在未知的危险外，还有着虎视眈眈的另一支势力…\n\n某个疲惫的深夜，准备休息的米卡突然收到了另一队前锋的警告：骑士团遭遇了敌情。\n\n米卡匆匆抵达现场时，法尔伽早已带着他的得力部下们摆开了战阵。\n\n夜幕深处，隐约可见高大士兵构成的人墙，他们无声伫立，似是没有生气的战争机器。\n\n而在对方阵线的中央，可见一道漆黑、锐利的身影。对方的面容似乎无法被火光照亮，唯有幽蓝的双目氤氲着摄人心魄的暗芒。\n\n在同僚的提醒下，米卡得知了对方的身份——愚人众执行官「队长」，以及直属他的尖兵。\n\n西风骑士团的前锋撞上了愚人众的前哨，发生了摩擦，双方的神经都太过敏感，不断申请增援，最终惊动了双方的最高长官。\n\n空气中的硝烟味太过浓烈，危机感迅速侵入米卡的脑海，让他四肢麻木，手脚冰凉。\n\n米卡不断想象，要是对峙演变成冲突，自己该怎么办…\n\n尤其是那位执行官，米卡只觉得，自己根本没可能招架住对方的随手一击。\n\n杂乱的念头和沉重的疲惫感让米卡呼吸加速，难以集中注意力。\n\n法尔伽却表现得游刃有余，遥遥向对方打了个招呼，提着武器独自走向「队长」。「队长」也示意部下待命，缓慢上前。\n\n在双方紧张到极点的情况下，法尔伽与「队长」进行了一番短暂的商谈。\n\n随后，漆黑的身影稍稍抬手，愚人众的尖兵们便跟在他身后一同离去，犹如鬼影消散，无声无息。\n\n在场的西风骑士们无不长舒一口气，甚至有人止不住战栗。可法尔伽回到骑士团的阵线后，还表现得轻松自在：\n\n「好一场偶遇！要不是现在的情况很特别，我还真想找个机会和他切磋两下！」\n\n「他不是个固执的家伙，他也明白，在陌生的土地上交战，对我们两边都没好处…」\n\n直到此时，米卡才深刻地意识到，自己刚刚踏在了战争的导火索上，好这根导火索并未被引燃。\n\n「队长」的强大压迫感、大团长处理危机时的稳重…这场对峙深深刻入了米卡的记忆。\n\n他反省良久：虽说自己的实力正在快速提升，但还是差了太多火候，根本没法从容应对这样的局面。\n\n不能只满足于为团队献出全力，必须再刻苦一点，变得更加可靠，妥善处理各种意外…\n\n### 角色故事5\n\n好在之后远征途中米卡再未遇到过分惊险的事，顺利度过了最为艰苦的时期。\n\n蒙德「归风佳酿节」期间，米卡带着大团长的信件重返蒙德，回归了游击小队。\n\n游击小队的同伴们欣喜之余也倍感惊奇：米卡的实力突飞猛进，原本三名前锋才能完成的任务如今只需他一人就能轻松搞定。\n\n考虑到大团长信中曾模糊地提到过愚人众，米卡则是直属大团长的骨干…随着同僚们议论不断，一条奇怪的逻辑链诞生了——\n\n「米卡和愚人众交过手！米卡大概和愚人众的精锐交过手！米卡有可能跟着大团长一起对付过愚人众的执行官！」\n\n「要不然，米卡怎么会突然变得这么强呢！现在他也是我们的大英雄了，不管什么事都可以拜托他！」\n\n实际上，米卡不过是在远征途中得到了充分的历练，其他西风骑士也有不同程度的进步，只不过他们还没归来，无法形成对比罢了。\n\n对于这些离谱的传言，米卡不知该怎么去解释，便请教了琴和凯亚。\n\n琴谨慎地告知各个小队的负责人，希望大家保持理智，不要传播缺少证据的消息，另外，远征中的许多事宜都属于军事机密，本就应谨慎对待。\n\n凯亚则不以为然，还在打趣——西风骑士们多多少少对愚人众有点怨言，「米卡痛揍愚人众」这样的传言，好像对士气有利呢。\n\n总之，既然代理团长已经知道这一情况，又没有给别人添麻烦…米卡也就不那么恐慌了。\n\n他一如既往地执勤，遇上请求帮助的同僚就尽全力伸出援手。\n\n只不过，传闻太夸张，太被别人信任，好像也会带来困扰…\n\n最近向米卡借阅新地图、请米卡帮忙维护武器、甚至是蹭一口游击小队行军餐的同僚都变多了。\n\n这些同僚好像都想得到「前进测绘员的气势」，让自己像米卡那样快快变强。\n\n### 「整合型前进测绘装置」\n\n米卡随身携带的精巧装置，形如一册厚重的书本。\n\n这件装置由米卡与调查小队的技术人员一同开发，关键部件采用了阿贝多最新的炼金术成果——\n\n装置内部安置了一本记事簿，可用于记录信息，每张纸页都能被快速拆卸替换，便于直接产出地图。\n\n外壳背部的板材中则蚀刻着致密的纹样，通过对纹样注入元素力即可激活背板外的棱形部件，向目标扇区释放探测用「波束」。\n\n接收「波束」碰撞目标物后反弹的回波，计算发射与接收的时间差，就能进行相对精准的测距；而不断加快释放「波束」的节奏，增大「波束」的宽度后，即可将一片狭小区域的地形立体地描摹。\n\n这一功能可以大大提高绘制地图时的准确度。可惜，一切探测所得的信息和计算过程都需要使用者用脑力来处理。\n\n只有原本就对于目标地形极为熟悉，能将平面地图准确记下，并具备极强空间认知力的精英，才能正常运用该功能。\n\n因此，能将这件装置顺利运用的前进测绘员，仅有米卡一人，使用的频率也不宜太高。\n\n原本计划列装其他小队的改进型设备最终都被储存起来，用来为米卡的装置提供零件。\n\n它是米卡作为最优秀的前进测绘员的得力助手与荣誉象征，但米卡从不向其他人提起它的精妙之处。\n\n那样的行为在米卡看来就像是一种炫耀，还有可能给阿贝多带去额外的工作，增添不少麻烦…避免为好。\n\n### 神之眼\n\n米卡曾经历一次生死攸关的危机。\n\n那是在刚刚加入游击小队后不久，米卡接到任务，照常独自行动，前往一片情报失效的区域，重新绘制那里的地形细节。\n\n他蹑手蹑脚地踏入废墟，却不慎碰落了断壁上的石块，惊扰了黑暗中的两位深渊法师。\n\n烈焰交织，元素的奔流瞬间吞没米卡，像是要将他彻底绞碎，蒸煮成魔物的佳肴。\n\n痛苦与慌乱侵入感官，唯有一个念头还留存在米卡的意识中——必须摆脱这些敌人，警告后方的同伴。\n\n「就算是游击小队的前辈…遭遇了这种伏击…也会陷入危险！」\n\n前进测绘员的职责，正是让同伴避开这样的险境。\n\n两位深渊法师拍手叫好，正要让其他潜藏的魔物解除伪装，旋转的长枪就已撕开火幕，漫天冰雾绽放，压制了废墟中的高温。\n\n等到深渊法师们回过神来，米卡已经远远逃开，还不忘高声道歉：\n\n「对不起！下次我会先敲门，让前辈们和你们堂堂正正对决的！」\n\n米卡口中的「下次」很快就到来了，游击小队的主力得到了情报，接踵而至，谨慎地清除了这些伏兵。\n\n同僚们讶异地发现，两名深渊法师的元素护罩早已残破不堪。看着米卡右腕光彩璀璨的「神之眼」，他们似乎明白了什么…\n\n那一天，游击小队的晚饭格外丰盛，大家都为米卡举杯庆祝，只有米卡本人还惊魂未定，云里雾里。"
  },
  "notes": {
    "general": "",
    "byVolume": {}
  },
  "story_group": "character_stories",
  "category_type": "character_stories",
  "elements": [
    "cryo"
  ],
  "element": "cryo"
}